Workbook
Name TGR: DCF!$D$19
Name WACC: DCF!$D$18

Sheet Trading Comp
B2: Comp Table
C3: As of 8/27/2025
B4: Date | C4: =TODAY() -> 46037
B5: Currency | C5: USD
Z7: Trading Mulitples
D8: Current | E8: Share | F8: Enterprise | G8: Market | I8: Revenue | L8: EBITDA | N8: Net Income | Q8: Revenue Growth | S8: EBITDA Margin | U8: Profit Margin | X8: EV / Revenue | Z8: EV / EBITDA | AB8: P / E
B9: Ticker | C9: Company Name | D9: Price | E9: Count | F9: Value | G9: Cap | I9: 22 | J9: 23 | K9: 24 | L9: 23 | M9: 24 | N9: 23 | O9: 24 | Q9: 22-23 | R9: 23-24 | S9: 23 | T9: 24 | U9: 23 | V9: 24 | X9: 23 | Y9: 24 | Z9: 23 | AA9: 24 | AB9: 23 | AC9: 24
B11: LULU | C11: =_xlfn.XLOOKUP($B11,$B$36:$B$47,C$36:C$47,,0) -> Lululemon | D11: =_xlfn.XLOOKUP($B11,$B$36:$B$47,D$36:D$47,,0) -> 205.57 | E11: =_xlfn.XLOOKUP($B11,$B$36:$B$47,E$36:E$47,,0) -> 116.37023 | F11: =_xlfn.XLOOKUP($B11,$B$36:$B$47,F$36:F$47,,0) -> 24272.29 | G11: =_xlfn.XLOOKUP($B11,$B$36:$B$47,G$36:G$47,,0) -> 23059.22 | I11: =_xlfn.XLOOKUP($B11,$B$36:$B$47,I$36:I$47,,0) -> 8111 | J11: =_xlfn.XLOOKUP($B11,$B$36:$B$47,J$36:J$47,,0) -> 9619 | K11: =_xlfn.XLOOKUP($B11,$B$36:$B$47,K$36:K$47,,0) -> 10588 | L11: =_xlfn.XLOOKUP($B11,$B$36:$B$47,L$36:L$47,,0) -> 2587 | M11: =_xlfn.XLOOKUP($B11,$B$36:$B$47,M$36:M$47,,0) -> 2946 | N11: =_xlfn.XLOOKUP($B11,$B$36:$B$47,N$36:N$47,,0) -> 1550 | O11: =_xlfn.XLOOKUP($B11,$B$36:$B$47,O$36:O$47,,0) -> 1815 | Q11: =J11/I11-1 -> 0.18592036 | R11: =K11/J11-1 -> 0.10073812 | S11: =L11/J11 -> 0.26894688 | T11: =M11/K11 -> 0.27823952 | U11: =N11/J11 -> 0.16113941 | V11: =O11/K11 -> 0.17142048 | X11: =$F11/J11 -> 2.5233694 | Y11: =$F11/K11 -> 2.2924339 | Z11: =$F11/L11 -> 9.3824082 | AA11: =$F11/M11 -> 8.2390665 | AB11: =$F11/N11 -> 15.659542 | AC11: =$F11/O11 -> 13.373163
A13: 1 | B13: COLM | C13: =_xlfn.XLOOKUP($B13,$B$36:$B$47,C$36:C$47,,0) -> Columbia Sportswear | D13: =_xlfn.XLOOKUP($B13,$B$36:$B$47,D$36:D$47,,0) -> 55.18 | E13: =_xlfn.XLOOKUP($B13,$B$36:$B$47,E$36:E$47,,0) -> 58.5 | F13: =_xlfn.XLOOKUP($B13,$B$36:$B$47,F$36:F$47,,0) -> 3022.21 | G13: =_xlfn.XLOOKUP($B13,$B$36:$B$47,G$36:G$47,,0) -> 2502.31 | I13: =_xlfn.XLOOKUP($B13,$B$36:$B$47,I$36:I$47,,0) -> 3464 | J13: =_xlfn.XLOOKUP($B13,$B$36:$B$47,J$36:J$47,,0) -> 3487 | K13: =_xlfn.XLOOKUP($B13,$B$36:$B$47,K$36:K$47,,0) -> 3370 | L13: =_xlfn.XLOOKUP($B13,$B$36:$B$47,L$36:L$47,,0) -> 441 | M13: =_xlfn.XLOOKUP($B13,$B$36:$B$47,M$36:M$47,,0) -> 322 | N13: =_xlfn.XLOOKUP($B13,$B$36:$B$47,N$36:N$47,,0) -> 251 | O13: =_xlfn.XLOOKUP($B13,$B$36:$B$47,O$36:O$47,,0) -> 223 | Q13: =J13/I13-1 -> 0.0066397229 | R13: =K13/J13-1 -> -0.033553198 | S13: =L13/J13 -> 0.12646974 | T13: =M13/K13 -> 0.095548961 | U13: =N13/J13 -> 0.071981646 | V13: =O13/K13 -> 0.066172107 | X13: =$F13/J13 -> 0.86670777 | Y13: =$F13/K13 -> 0.89679822 | Z13: =$F13/L13 -> 6.8530839 | AA13: =$F13/M13 -> 9.3857453 | AB13: =$F13/N13 -> 12.040677 | AC13: =$F13/O13 -> 13.552511
A14: 2 | B14: UAA | C14: =_xlfn.XLOOKUP($B14,$B$36:$B$47,C$36:C$47,,0) -> Under Armour | D14: =_xlfn.XLOOKUP($B14,$B$36:$B$47,D$36:D$47,,0) -> 5.04 | E14: =_xlfn.XLOOKUP($B14,$B$36:$B$47,E$36:E$47,,0) -> 432.25 | F14: =_xlfn.XLOOKUP($B14,$B$36:$B$47,F$36:F$47,,0) -> 2142.76 | G14: =_xlfn.XLOOKUP($B14,$B$36:$B$47,G$36:G$47,,0) -> 2346.62 | I14: =_xlfn.XLOOKUP($B14,$B$36:$B$47,I$36:I$47,,0) -> 5859 | J14: =_xlfn.XLOOKUP($B14,$B$36:$B$47,J$36:J$47,,0) -> 5694 | K14: =_xlfn.XLOOKUP($B14,$B$36:$B$47,K$36:K$47,,0) -> 5166 | L14: =_xlfn.XLOOKUP($B14,$B$36:$B$47,L$36:L$47,,0) -> 375 | M14: =_xlfn.XLOOKUP($B14,$B$36:$B$47,M$36:M$47,,0) -> 307 | N14: =_xlfn.XLOOKUP($B14,$B$36:$B$47,N$36:N$47,,0) -> 232 | O14: =_xlfn.XLOOKUP($B14,$B$36:$B$47,O$36:O$47,,0) -> -201 | Q14: =J14/I14-1 -> -0.028161802 | R14: =K14/J14-1 -> -0.092729189 | S14: =L14/J14 -> 0.065858799 | T14: =M14/K14 -> 0.059427023 | U14: =N14/J14 -> 0.040744643 | V14: =O14/K14 -> -0.038908246 | X14: =$F14/J14 -> 0.37631893 | Y14: =$F14/K14 -> 0.41478126 | Z14: =$F14/L14 -> 5.7140267 | AA14: =$F14/M14 -> 6.9796743 | AB14: =$F14/N14 -> 9.2360345 | AC14: =$F14/O14 -> -10.660498
A15: 3 | B15: ATZAF | C15: =_xlfn.XLOOKUP($B15,$B$36:$B$47,C$36:C$47,,0) -> Artizia | D15: =_xlfn.XLOOKUP($B15,$B$36:$B$47,D$36:D$47,,0) -> 57.48 | E15: =_xlfn.XLOOKUP($B15,$B$36:$B$47,E$36:E$47,,0) -> 116.73 | F15: =_xlfn.XLOOKUP($B15,$B$36:$B$47,F$36:F$47,,0) -> 6579.19 | G15: =_xlfn.XLOOKUP($B15,$B$36:$B$47,G$36:G$47,,0) -> 6722.82 | I15: =_xlfn.XLOOKUP($B15,$B$36:$B$47,I$36:I$47,,0) -> 1670.9 | J15: =_xlfn.XLOOKUP($B15,$B$36:$B$47,J$36:J$47,,0) -> 1727.6 | K15: =_xlfn.XLOOKUP($B15,$B$36:$B$47,K$36:K$47,,0) -> 1977.8 | L15: =_xlfn.XLOOKUP($B15,$B$36:$B$47,L$36:L$47,,0) -> 241.8 | M15: =_xlfn.XLOOKUP($B15,$B$36:$B$47,M$36:M$47,,0) -> 347.8 | N15: =_xlfn.XLOOKUP($B15,$B$36:$B$47,N$36:N$47,,0) -> 58.4 | O15: =_xlfn.XLOOKUP($B15,$B$36:$B$47,O$36:O$47,,0) -> 150.1 | Q15: =J15/I15-1 -> 0.033933808 | R15: =K15/J15-1 -> 0.14482519 | S15: =L15/J15 -> 0.13996295 | T15: =M15/K15 -> 0.17585196 | U15: =N15/J15 -> 0.033804121 | V15: =O15/K15 -> 0.075892406 | X15: =$F15/J15 -> 3.8082832 | Y15: =$F15/K15 -> 3.3265194 | Z15: =$F15/L15 -> 27.209222 | AA15: =$F15/M15 -> 18.91659 | AB15: =$F15/N15 -> 112.65736 | AC15: =$F15/O15 -> 43.832045
A16: 4 | B16: NIKE | C16: =_xlfn.XLOOKUP($B16,$B$36:$B$47,C$36:C$47,,0) -> Nike | D16: =_xlfn.XLOOKUP($B16,$B$36:$B$47,D$36:D$47,,0) -> 78.06 | E16: =_xlfn.XLOOKUP($B16,$B$36:$B$47,E$36:E$47,,0) -> 1487.6 | F16: =_xlfn.XLOOKUP($B16,$B$36:$B$47,F$36:F$47,,0) -> 115287.09 | G16: =_xlfn.XLOOKUP($B16,$B$36:$B$47,G$36:G$47,,0) -> 114937.33 | I16: =_xlfn.XLOOKUP($B16,$B$36:$B$47,I$36:I$47,,0) -> 46792 | J16: =_xlfn.XLOOKUP($B16,$B$36:$B$47,J$36:J$47,,0) -> 51191 | K16: =_xlfn.XLOOKUP($B16,$B$36:$B$47,K$36:K$47,,0) -> 51386 | L16: =_xlfn.XLOOKUP($B16,$B$36:$B$47,L$36:L$47,,0) -> 6016 | M16: =_xlfn.XLOOKUP($B16,$B$36:$B$47,M$36:M$47,,0) -> 6839 | N16: =_xlfn.XLOOKUP($B16,$B$36:$B$47,N$36:N$47,,0) -> 5070 | O16: =_xlfn.XLOOKUP($B16,$B$36:$B$47,O$36:O$47,,0) -> 5700 | Q16: =J16/I16-1 -> 0.094011797 | R16: =K16/J16-1 -> 0.0038092633 | S16: =L16/J16 -> 0.11752066 | T16: =M16/K16 -> 0.13309073 | U16: =N16/J16 -> 0.099040847 | V16: =O16/K16 -> 0.11092515 | X16: =$F16/J16 -> 2.2520969 | Y16: =$F16/K16 -> 2.2435506 | Z16: =$F16/L16 -> 19.163413 | AA16: =$F16/M16 -> 16.857302 | AB16: =$F16/N16 -> 22.739071 | AC16: =$F16/O16 -> 20.225805
A17: 5 | B17: ADDDF | C17: =_xlfn.XLOOKUP($B17,$B$36:$B$47,C$36:C$47,,0) -> Adidas | D17: =_xlfn.XLOOKUP($B17,$B$36:$B$47,D$36:D$47,,0) -> 194.69 | E17: =_xlfn.XLOOKUP($B17,$B$36:$B$47,E$36:E$47,,0) -> 178.56 | F17: =_xlfn.XLOOKUP($B17,$B$36:$B$47,F$36:F$47,,0) -> 34895.2 | G17: =_xlfn.XLOOKUP($B17,$B$36:$B$47,G$36:G$47,,0) -> 37627.2 | I17: =_xlfn.XLOOKUP($B17,$B$36:$B$47,I$36:I$47,,0) -> 23658 | J17: =_xlfn.XLOOKUP($B17,$B$36:$B$47,J$36:J$47,,0) -> 23165 | K17: =_xlfn.XLOOKUP($B17,$B$36:$B$47,K$36:K$47,,0) -> 25618 | L17: =_xlfn.XLOOKUP($B17,$B$36:$B$47,L$36:L$47,,0) -> 1463 | M17: =_xlfn.XLOOKUP($B17,$B$36:$B$47,M$36:M$47,,0) -> 2618 | N17: =_xlfn.XLOOKUP($B17,$B$36:$B$47,N$36:N$47,,0) -> -129 | O17: =_xlfn.XLOOKUP($B17,$B$36:$B$47,O$36:O$47,,0) -> 818 | Q17: =J17/I17-1 -> -0.020838617 | R17: =K17/J17-1 -> 0.10589251 | S17: =L17/J17 -> 0.063155623 | T17: =M17/K17 -> 0.10219377 | U17: =N17/J17 -> -0.005568746 | V17: =O17/K17 -> 0.031930674 | X17: =$F17/J17 -> 1.506376 | Y17: =$F17/K17 -> 1.362136 | Z17: =$F17/L17 -> 23.851811 | AA17: =$F17/M17 -> 13.328953 | AB17: =$F17/N17 -> -270.50543 | AC17: =$F17/O17 -> 42.659169
A18: 6 | B18: RL | C18: =_xlfn.XLOOKUP($B18,$B$36:$B$47,C$36:C$47,,0) -> Ralph Lauren Corporation | D18: =_xlfn.XLOOKUP($B18,$B$36:$B$47,D$36:D$47,,0) -> 294.64 | E18: =_xlfn.XLOOKUP($B18,$B$36:$B$47,E$36:E$47,,0) -> 64 | F18: =_xlfn.XLOOKUP($B18,$B$36:$B$47,F$36:F$47,,0) -> 17765.87 | G18: =_xlfn.XLOOKUP($B18,$B$36:$B$47,G$36:G$47,,0) -> 17498.34 | I18: =_xlfn.XLOOKUP($B18,$B$36:$B$47,I$36:I$47,,0) -> 6219 | J18: =_xlfn.XLOOKUP($B18,$B$36:$B$47,J$36:J$47,,0) -> 6444 | K18: =_xlfn.XLOOKUP($B18,$B$36:$B$47,K$36:K$47,,0) -> 6631 | L18: =_xlfn.XLOOKUP($B18,$B$36:$B$47,L$36:L$47,,0) -> 967 | M18: =_xlfn.XLOOKUP($B18,$B$36:$B$47,M$36:M$47,,0) -> 1045 | N18: =_xlfn.XLOOKUP($B18,$B$36:$B$47,N$36:N$47,,0) -> 523 | O18: =_xlfn.XLOOKUP($B18,$B$36:$B$47,O$36:O$47,,0) -> 646 | Q18: =J18/I18-1 -> 0.03617945 | R18: =K18/J18-1 -> 0.029019243 | S18: =L18/J18 -> 0.15006207 | T18: =M18/K18 -> 0.15759312 | U18: =N18/J18 -> 0.08116077 | V18: =O18/K18 -> 0.097421203 | X18: =$F18/J18 -> 2.7569631 | Y18: =$F18/K18 -> 2.6792143 | Z18: =$F18/L18 -> 18.372151 | AA18: =$F18/M18 -> 17.000833 | AB18: =$F18/N18 -> 33.969159 | AC18: =$F18/O18 -> 27.501347
A19: 7 | B19: DKS | C19: =_xlfn.XLOOKUP($B19,$B$36:$B$47,C$36:C$47,,0) -> Dick's Sporting Goods | D19: =_xlfn.XLOOKUP($B19,$B$36:$B$47,D$36:D$47,,0) -> 226.01 | E19: =_xlfn.XLOOKUP($B19,$B$36:$B$47,E$36:E$47,,0) -> 82.93 | F19: =_xlfn.XLOOKUP($B19,$B$36:$B$47,F$36:F$47,,0) -> 18165.96 | G19: =_xlfn.XLOOKUP($B19,$B$36:$B$47,G$36:G$47,,0) -> 19070.8 | I19: =_xlfn.XLOOKUP($B19,$B$36:$B$47,I$36:I$47,,0) -> 12368 | J19: =_xlfn.XLOOKUP($B19,$B$36:$B$47,J$36:J$47,,0) -> 12984 | K19: =_xlfn.XLOOKUP($B19,$B$36:$B$47,K$36:K$47,,0) -> 13443 | L19: =_xlfn.XLOOKUP($B19,$B$36:$B$47,L$36:L$47,,0) -> 1770 | M19: =_xlfn.XLOOKUP($B19,$B$36:$B$47,M$36:M$47,,0) -> 1929 | N19: =_xlfn.XLOOKUP($B19,$B$36:$B$47,N$36:N$47,,0) -> 1047 | O19: =_xlfn.XLOOKUP($B19,$B$36:$B$47,O$36:O$47,,0) -> 1165 | Q19: =J19/I19-1 -> 0.049805951 | R19: =K19/J19-1 -> 0.035351201 | S19: =L19/J19 -> 0.13632163 | T19: =M19/K19 -> 0.14349476 | U19: =N19/J19 -> 0.080637708 | V19: =O19/K19 -> 0.086662203 | X19: =$F19/J19 -> 1.3991035 | Y19: =$F19/K19 -> 1.3513323 | Z19: =$F19/L19 -> 10.263254 | AA19: =$F19/M19 -> 9.4172939 | AB19: =$F19/N19 -> 17.350487 | AC19: =$F19/O19 -> 15.593099
B21: Mean | Q21: =AVERAGE(Q11:Q19) -> 0.044686333 | R21: =AVERAGE(R11:R19) -> 0.036669143 | S21: =AVERAGE(S11:S19) -> 0.13353729 | T21: =AVERAGE(T11:T19) -> 0.14317998 | U21: =AVERAGE(U11:U19) -> 0.07036755 | V21: =AVERAGE(V11:V19) -> 0.075189497 | X21: =AVERAGE(X11:X19) -> 1.9361523 | Y21: =AVERAGE(Y11:Y19) -> 1.8208457 | Z21: =AVERAGE(Z11:Z19) -> 15.101171 | AA21: =AVERAGE(AA11:AA19) -> 12.515682 | AB21: =AVERAGE(AB11:AB19) -> -5.8566366 | AC21: =AVERAGE(AC11:AC19) -> 20.75958
B22: Median | Q22: =MEDIAN(Q11:Q19) -> 0.035056629 | R22: =MEDIAN(R11:R19) -> 0.032185222 | S22: =MEDIAN(S11:S19) -> 0.13139569 | T22: =MEDIAN(T11:T19) -> 0.13829274 | U22: =MEDIAN(U11:U19) -> 0.076309677 | V22: =MEDIAN(V11:V19) -> 0.081277305 | X22: =MEDIAN(X11:X19) -> 1.8792364 | Y22: =MEDIAN(Y11:Y19) -> 1.8028433 | Z22: =MEDIAN(Z11:Z19) -> 14.317703 | AA22: =MEDIAN(AA11:AA19) -> 11.373124 | AB22: =MEDIAN(AB11:AB19) -> 16.505015 | AC22: =MEDIAN(AC11:AC19) -> 17.909452
D24: 2024 Trading Multiple | H24: 2024 Financial Metric | L24: Enterprise Value | Q24: 2024 | T24: Equity Value | X24: Implied Share Price
B25: Calculating Implied Share Price | D25: Revenue | E25: EBITDA | F25: P/E | H25: Revenue | I25: EBITDA | J25: EPS | L25: Revenue | M25: EBITDA | N25: Net Income | P25: Cash | Q25: Debt | R25: Shares | T25: Revenue | U25: EBITDA | V25: Net Income | X25: Revenue | Y25: EBITDA | Z25: Net Income
B26: Minimum | D26: =MIN(Y13:Y19) -> 0.41478126 | E26: =MIN(AA13:AA19) -> 6.9796743 | F26: =MIN(AC13:AC19) -> -10.660498 | H26: =$K$11 -> 10588 | I26: =$M$11 -> 2946 | J26: 14.64 | L26: =H26*D26 -> 4391.704 | M26: =I26*E26 -> 20562.12 | P26: =DCF!$R$150 -> 1984.336 | Q26: =DCF!$R$151 -> 1575.8 | R26: 116.37023 | T26: =L26+P26-Q26 -> 4800.24 | U26: =M26+P26-Q26 -> 20970.656 | V26: =J26*R26*F26 -> -18161.865 | X26: =T26/$R26 -> 41.249725 | Y26: =U26/$R26 -> 180.20637 | Z26: =V26/$R26 -> -156.06968
B27: Mean | D27: =Y21 -> 1.8208457 | E27: =AA21 -> 12.515682 | F27: =AC21 -> 20.75958 | H27: =$K$11 -> 10588 | I27: =$M$11 -> 2946 | J27: 14.64 | L27: =H27*D27 -> 19279.115 | M27: =I27*E27 -> 36871.2 | P27: =DCF!$R$150 -> 1984.336 | Q27: =DCF!$R$151 -> 1575.8 | R27: 116.37023 | T27: =L27+P27-Q27 -> 19687.651 | U27: =M27+P27-Q27 -> 37279.736 | V27: =J27*R27*F27 -> 35367.27 | X27: =T27/$R27 -> 169.18116 | Y27: =U27/$R27 -> 320.35458 | Z27: =V27/$R27 -> 303.92025
B28: Median | D28: =Y22 -> 1.8028433 | E28: =AA22 -> 11.373124 | F28: =AC22 -> 17.909452 | H28: =$K$11 -> 10588 | I28: =$M$11 -> 2946 | J28: 14.64 | L28: =H28*D28 -> 19088.505 | M28: =I28*E28 -> 33505.222 | P28: =DCF!$R$150 -> 1984.336 | Q28: =DCF!$R$151 -> 1575.8 | R28: 116.37023 | T28: =L28+P28-Q28 -> 19497.041 | U28: =M28+P28-Q28 -> 33913.758 | V28: =J28*R28*F28 -> 30511.62 | X28: =T28/$R28 -> 167.5432 | Y28: =U28/$R28 -> 291.42984 | Z28: =V28/$R28 -> 262.19438
B29: Maximum | D29: =MAX(Y13:Y19) -> 3.3265194 | E29: =MAX(AA13:AA19) -> 18.91659 | F29: =MAX(AC13:AC19) -> 43.832045 | H29: =$K$11 -> 10588 | I29: =$M$11 -> 2946 | J29: 14.64 | L29: =H29*D29 -> 35221.187 | M29: =I29*E29 -> 55728.274 | P29: =DCF!$R$150 -> 1984.336 | Q29: =DCF!$R$151 -> 1575.8 | R29: 116.37023 | T29: =L29+P29-Q29 -> 35629.723 | U29: =M29+P29-Q29 -> 56136.81 | V29: =J29*R29*F29 -> 74674.91 | X29: =T29/$R29 -> 306.17558 | Y29: =U29/$R29 -> 482.39837 | Z29: =V29/$R29 -> 641.70114
B31: Database
D34: Current | E34: Share | F34: Market | G34: Enterprise | I34: Revenue | L34: EBITDA | N34: Net Income
B35: Ticker | C35: Company Name | D35: Price | E35: Count | F35: Cap | G35: Value | I35: 22 | J35: 23 | K35: 24 | L35: 23 | M35: 24 | N35: 23 | O35: 24
B36: LULU | C36: Lululemon | D36: 205.57 | E36: 116.37023 | F36: 24272.29 | G36: 23059.22 | I36: 8111 | J36: 9619 | K36: 10588 | L36: 2587 | M36: 2946 | N36: 1550 | O36: 1815
B37: COLM | C37: Columbia Sportswear | D37: 55.18 | E37: 58.5 | F37: 3022.21 | G37: 2502.31 | I37: 3464 | J37: 3487 | K37: 3370 | L37: 441 | M37: 322 | N37: 251 | O37: 223
B38: UAA | C38: Under Armour | D38: 5.04 | E38: 432.25 | F38: 2142.76 | G38: 2346.62 | I38: 5859 | J38: 5694 | K38: 5166 | L38: 375 | M38: 307 | N38: 232 | O38: -201
B39: ATZAF | C39: Artizia | D39: 57.48 | E39: 116.73 | F39: 6579.19 | G39: 6722.82 | I39: 1670.9 | J39: 1727.6 | K39: 1977.8 | L39: 241.8 | M39: 347.8 | N39: 58.4 | O39: 150.1
B40: NIKE | C40: Nike | D40: 78.06 | E40: 1487.6 | F40: 115287.09 | G40: 114937.33 | I40: 46792 | J40: 51191 | K40: 51386 | L40: 6016 | M40: 6839 | N40: 5070 | O40: 5700
B41: ADDDF | C41: Adidas | D41: 194.69 | E41: 178.56 | F41: 34895.2 | G41: 37627.2 | I41: 23658 | J41: 23165 | K41: 25618 | L41: 1463 | M41: 2618 | N41: -129 | O41: 818
B42: RL | C42: Ralph Lauren Corporation | D42: 294.64 | E42: 64 | F42: 17765.87 | G42: 17498.34 | I42: 6219 | J42: 6444 | K42: 6631 | L42: 967 | M42: 1045 | N42: 523 | O42: 646
B43: DKS | C43: Dick's Sporting Goods | D43: 226.01 | E43: 82.93 | F43: 18165.96 | G43: 19070.8 | I43: 12368 | J43: 12984 | K43: 13443 | L43: 1770 | M43: 1929 | N43: 1047 | O43: 1165
B44: GAP | C44: Gap | D44: 22.3 | E44: 384 | F44: 8319.38 | G44: 7987.39 | I44: 15616 | J44: 14889 | K44: 15086 | L44: 1144 | M44: 1600 | N44: 502 | O44: 844

Sheet DCF
B1: Allen Li
B2: Lululemon DCF
B4: Ticker | C4: LULU-US | F4: Current Price | I4: ='Trading Comp'!D36 -> 205.57 | K4: Green | L4: Reference other sheet
B5: Date | C5: =TODAY() -> 46037 | F5: Implied Share Price | I5: =R155 -> 231.98052 | K5: Red | L5: Reference estimations
B6: Year End | C6: 46022 | F6: Gain (Loss) | I6: =I5/I4-1 -> 0.1284746 | K6: Black | L6: Calculations
K7: Purple | L7: Repeat from cell
A9: x | B9: Assumptions
B10: Switches | F10: Conservative | J10: Base | N10: Optimistic
B11: Revenue | D11: 2 | F11: Revenue 26-29 | H11: 0.8 | J11: Revenue 27 | L11: 0.08 | N11: Revenue 26-29 | P11: 1.2
B12: EBIT | D12: 2 | F12: EBIT 26-29 | H12: 0.9 | J12: Revenue 29 | L12: 0.06 | N12: EBIT 26-29 | P12: 1.1
B13: WACC | D13: 2 | F13: SL Revenue | J13: EBIT 29 | L13: 0.21 | N13: SL Revenue
B14: TGR | D14: 2 | F14: SL EBIT | J14: SL Revenue | N14: SL EBIT
B15: Decay Factor | D15: 1 | J15: SL EBIT
F17: WACC | H17: =L17+0.5% -> 0.089126282 | J17: WACC | L17: =WACC!F21 -> 0.084126282 | N17: WACC | P17: =L17-0.5% -> 0.079126282
B18: WACC | D18: =CHOOSE($D$13,H17,L17,P17) -> 0.084126282 | F18: TGR | H18: 0.02 | J18: TGR | L18: 0.025 | N18: TGR | P18: 0.03
B19: TCG | D19: =CHOOSE(D14,H18,L18,P18) -> 0.025 | J19: Taxes | L19: =N128 -> 0.29833566
A21: x | B21: Revenue (12/31 CYE) | D21: 2015 | E21: 2016 | F21: 2017 | G21: 2018 | H21: 2019 | I21: 2020 | J21: 2021 | K21: 2022 | L21: 2023 | M21: 2024 | N21: 2025E | O21: 2026E | P21: 2027E | Q21: 2028E | R21: 2029E
H22: 67
B23: Company-operating stores | D23: 1516.323 | E23: 1704.357 | F23: 1837.065 | G23: 2126.363 | H23: 2501.067 | I23: 1658.807 | J23: 2821.497 | K23: 3648.127 | L23: =L38*L25 -> 4096.545 | M23: =M38*M25 -> 4509.1466 | N23: =N38*N25 -> 4780.7117 | O23: =O38*O25 -> 5110.8447 | P23: =P38*P25 -> 5422.3673 | Q23: =Q38*Q25 -> 5603.8724 | R23: =R38*R25 -> 6091.6193
B24: % growth | E24: =E23/D23-1 -> 0.12400656 | F24: =F23/E23-1 -> 0.077863969 | G24: =G23/F23-1 -> 0.15747837 | H24: =H23/G23-1 -> 0.17621827 | I24: =I23/H23-1 -> -0.33676027 | J24: =J23/I23-1 -> 0.7009194 | K24: =K23/J23-1 -> 0.29297568 | L24: =L23/K23-1 -> 0.12291731 | ... R24: =R23/Q23-1 -> 0.087037473
B25: % of total sales | D25: =D23/D35 -> 0.7358923 | E25: =E23/E35 -> 0.72699318 | F25: =F23/F35 -> 0.69344639 | G25: =G23/G35 -> 0.64664134 | H25: =H23/H35 -> 0.62851997 | I25: =I23/I35 -> 0.37684066 | J25: =J23/J35 -> 0.45096208 | K25: =K23/K35 -> 0.44980197 | L25: =AVERAGE($I$25:$K$25) -> 0.42586824 | M25: =AVERAGE($I$25:$K$25) -> 0.42586824 | N25: =AVERAGE($I$25:$M$25) -> 0.42586824 | O25: =AVERAGE($I$25:$M$25) -> 0.42586824 | P25: =AVERAGE($I$25:$M$25) -> 0.42586824 | Q25: =AVERAGE($I$25:$M$25) -> 0.42586824 | R25: =AVERAGE($I$25:$M$25) -> 0.42586824
B27: Direct to Consumer | D27: 401.525 | E27: 453.287 | F27: 577.59 | G27: 858.856 | H27: 1137.822 | I27: 2284.068 | J27: 2777.944 | K27: 3699.791 | L27: =L38*L29 -> 4550.1036 | M27: =M38*M29 -> 5008.3873 | N27: =N38*N29 -> 5310.0194 | O27: =O38*O29 -> 5676.7039 | P27: =P38*P29 -> 6022.7175 | Q27: =Q38*Q29 -> 6224.3183 | R27: =R38*R29 -> 6766.0672
B28: % growth | E28: =E27/D27-1 -> 0.12891352 | F28: =F27/E27-1 -> 0.27422582 | G28: =G27/F27-1 -> 0.4869648 | H28: =H27/G27-1 -> 0.32481114 | I28: =I27/H27-1 -> 1.0074036 | J28: =J27/I27-1 -> 0.21622649 | K28: =K27/J27-1 -> 0.33184506 | L28: =L27/K27-1 -> 0.22982719 | ... R28: =R27/Q27-1 -> 0.087037473
B29: % of total sales | D29: =D27/D35 -> 0.19486558 | E29: =E27/E35 -> 0.19334949 | F29: =F27/F35 -> 0.21802587 | G29: =G27/G35 -> 0.26118391 | H29: =H27/H35 -> 0.2859355 | I29: =I27/I35 -> 0.51888478 | J29: =J27/J35 -> 0.44400097 | K29: =K27/K35 -> 0.45617197 | L29: =AVERAGE($I$29:$K$29) -> 0.47301924 | M29: =AVERAGE($I$29:$K$29) -> 0.47301924 | N29: =AVERAGE($I$29:$M$29) -> 0.47301924 | O29: =AVERAGE($I$29:$M$29) -> 0.47301924 | P29: =AVERAGE($I$29:$M$29) -> 0.47301924 | Q29: =AVERAGE($I$29:$M$29) -> 0.47301924 | R29: =AVERAGE($I$29:$M$29) -> 0.47301924
L30: .
B31: Other | D31: 142.675 | E31: 186.748 | F31: 234.526 | G31: 303.1 | H31: 340.407 | I31: 459.004 | J31: 657.176 | K31: 762.6 | L31: =L38*L33 -> 972.62947 | M31: =M38*M33 -> 1070.5921 | N31: =N38*N33 -> 1135.069 | O31: =O38*O33 -> 1213.4514 | P31: =P38*P33 -> 1287.4152 | Q31: =Q38*Q33 -> 1330.5094 | R31: =R38*R33 -> 1446.3135
B32: % growth | E32: =E31/D31-1 -> 0.30890485 | F32: =F31/E31-1 -> 0.2558421 | G32: =G31/F31-1 -> 0.29239402 | H32: =H31/G31-1 -> 0.12308479 | I32: =I31/H31-1 -> 0.34839765 | J32: =J31/I31-1 -> 0.43174351 | K32: =K31/J31-1 -> 0.16041974 | L32: =L31/K31-1 -> 0.27541237 | ... R32: =R31/Q31-1 -> 0.087037473
B33: % of total sales | D33: =D31/D35 -> 0.069242129 | E33: =E31/E35 -> 0.079657327 | F33: =F31/F35 -> 0.088527737 | G33: =G31/G35 -> 0.092174756 | H33: =H31/H35 -> 0.085544528 | I33: =I31/I35 -> 0.10427456 | J33: =J31/J35 -> 0.10503696 | K33: =K31/K35 -> 0.094026054 | L33: =AVERAGE($I$33:$K$33) -> 0.10111252 | M33: =AVERAGE($I$33:$K$33) -> 0.10111252 | N33: =AVERAGE($I$33:$M$33) -> 0.10111252 | O33: =AVERAGE($I$33:$M$33) -> 0.10111252 | P33: =AVERAGE($I$33:$M$33) -> 0.10111252 | Q33: =AVERAGE($I$33:$M$33) -> 0.10111252 | R33: =AVERAGE($I$33:$M$33) -> 0.10111252
B35: Total | D35: =SUM(D23,D27,D31) -> 2060.523 | E35: =SUM(E23,E27,E31) -> 2344.392 | F35: =SUM(F23,F27,F31) -> 2649.181 | G35: =SUM(G23,G27,G31) -> 3288.319 | H35: =SUM(H23,H27,H31) -> 3979.296 | I35: =SUM(I23,I27,I31) -> 4401.879 | J35: =SUM(J23,J27,J31) -> 6256.617 | K35: =SUM(K23,K27,K31) -> 8110.518 | ... R35: =SUM(R23,R27,R31) -> 14304
B36: % growth | D36: -- | E36: =E35/D35-1 -> 0.13776551 | F36: =F35/E35-1 -> 0.13000769 | G36: =G35/F35-1 -> 0.24125871 | H36: =H35/G35-1 -> 0.21013077 | I36: =I35/H35-1 -> 0.10619542 | J36: =J35/I35-1 -> 0.42135143 | K36: =K35/J35-1 -> 0.29631045 | L36: =L35/K35-1 -> 0.18602511 | ... R36: =R35/Q35-1 -> 0.087037473
B38: Revenue | D38: =IS!B10 -> 2060.523 | E38: =IS!C10 -> 2344.392 | F38: =IS!D10 -> 2649.181 | G38: =IS!E10 -> 3288.319 | H38: =IS!F10 -> 3979.296 | I38: =IS!G10 -> 4401.879 | J38: =IS!H10 -> 6256.617 | K38: =IS!I10 -> 8110.518 | ... M38: =IS!K10 -> 10588.126 | N38: =IS!G60 -> 11225.8 | O38: =IS!H60 -> 12001 | P38: =IS!I60 -> 12732.5 | Q38: =IS!J60 -> 13158.7 | R38: =IS!K60 -> 14304
B39: % growth | E39: =E38/D38-1 -> 0.13776551 | F39: =F38/E38-1 -> 0.13000769 | G39: =G38/F38-1 -> 0.24125871 | H39: =H38/G38-1 -> 0.21013077 | I39: =I38/H38-1 -> 0.10619542 | J39: =J38/I38-1 -> 0.42135143 | K39: =K38/J38-1 -> 0.29631045 | L39: =L38/K38-1 -> 0.18602511 | ... R39: =R38/Q38-1 -> 0.087037473
B41: EBIT (12/31 CYE) | D41: 2015 | E41: 2016 | F41: 2017 | G41: 2018 | H41: 2019 | I41: 2020 | J41: 2021 | K41: 2022 | L41: 2023 | M41: 2024 | N41: 2025E | O41: 2026E | P41: 2027E | Q41: 2028E | R41: 2029E
B43: Company-operating stores | D43: =D55*D25 -> 262.80038 | E43: =E55*E25 -> 312.20868 | F43: =F55*F25 -> 343.88492 | G43: =G55*G25 -> 455.52196 | H43: =H55*H25 -> 559.7712 | I43: =I55*I25 -> 307.43867 | J43: =J55*J25 -> 623.73106 | K43: =K55*K25 -> 779.81089 | ... R43: =R55*R25 -> 1344.8919
B44: % of sales | D44: =D43/D23 -> 0.17331425 | E44: =E43/E23 -> 0.18318268 | F44: =F43/F23 -> 0.18719257 | G44: =G43/G23 -> 0.21422587 | H44: =H43/H23 -> 0.22381296 | I44: =I43/I23 -> 0.18533722 | J44: =J43/J23 -> 0.22106388 | K44: =K43/K23 -> 0.21375651 | ... R44: =R43/R23 -> 0.2207774
B45: % of total EBIT | D45: =D43/$D$55 -> 0.7358923 | E45: =E43/E55 -> 0.72699318 | F45: =F43/F55 -> 0.69344639 | G45: =G43/G55 -> 0.64664134 | H45: =H43/H55 -> 0.62851997 | I45: =I43/I55 -> 0.37684066 | J45: =J43/J55 -> 0.45096208 | K45: =K43/K55 -> 0.44980197 | L45: =L43/L55 -> 0.42586824 | ... R45: =R43/R55 -> 0.42586824
B47: Direct to Consumer | D47: =D55*D29 -> 69.590005 | E47: =E55*E29 -> 83.034326 | F47: =F55*F29 -> 108.12056 | G47: =G55*G29 -> 183.98917 | H47: =H55*H29 -> 254.65931 | I47: =I55*I29 -> 423.3228 | J47: =J55*J29 -> 614.10307 | K47: =K55*K29 -> 790.8544 | ... R47: =R55*R29 -> 1493.7948
B48: % of sales | D48: =D47/D27 -> 0.17331425 | E48: =E47/E27 -> 0.18318268 | F48: =F47/F27 -> 0.18719257 | G48: =G47/G27 -> 0.21422587 | H48: =H47/H27 -> 0.22381296 | I48: =I47/I27 -> 0.18533722 | J48: =J47/J27 -> 0.22106388 | K48: =K47/K27 -> 0.21375651 | ... R48: =R47/R27 -> 0.2207774
B49: % of total EBIT | D49: =D47/D$55 -> 0.19486558 | E49: =E47/E$55 -> 0.19334949 | F49: =F47/F$55 -> 0.21802587 | G49: =G47/G$55 -> 0.26118391 | H49: =H47/H$55 -> 0.2859355 | I49: =I47/I$55 -> 0.51888478 | J49: =J47/J$55 -> 0.44400097 | K49: =K47/K$55 -> 0.45617197 | ... R49: =R47/R$55 -> 0.47301924
B51: Other | D51: =D55*D33 -> 24.727611 | E51: =E55*E33 -> 34.208998 | F51: =F55*F33 -> 43.901525 | G51: =G55*G33 -> 64.931861 | H51: =H55*H33 -> 76.187497 | I51: =I55*I33 -> 85.070524 | J51: =J55*J33 -> 145.27787 | K51: =K55*K33 -> 163.01071 | ... R51: =R55*R33 -> 319.31335
B52: % of sales | D52: =D51/D31 -> 0.17331425 | E52: =E51/E31 -> 0.18318268 | F52: =F51/F31 -> 0.18719257 | G52: =G51/G31 -> 0.21422587 | H52: =H51/H31 -> 0.22381296 | I52: =I51/I31 -> 0.18533722 | J52: =J51/J31 -> 0.22106388 | K52: =K51/K31 -> 0.21375651 | ... R52: =R51/R31 -> 0.2207774
B53: % of total EBIT | D53: =D51/D$55 -> 0.069242129 | E53: =E51/E$55 -> 0.079657327 | F53: =F51/F$55 -> 0.088527737 | G53: =G51/G$55 -> 0.092174756 | H53: =H51/H$55 -> 0.085544528 | I53: =I51/I$55 -> 0.10427456 | J53: =J51/J$55 -> 0.10503696 | K53: =K51/K$55 -> 0.094026054 | ... R53: =R51/R$55 -> 0.10111252
B55: EBIT | D55: =IS!B19 -> 357.118 | E55: =IS!C19 -> 429.452 | F55: =IS!D19 -> 495.907 | G55: =IS!E19 -> 704.443 | H55: =IS!F19 -> 890.618 | I55: =IS!G19 -> 815.832 | J55: =IS!H19 -> 1383.112 | K55: =IS!I19 -> 1733.676 | ... M55: =IS!K19 -> 2499.777 | N55: =IS!G66 -> 2448.3 | O55: =IS!H66 -> 2583.99 | P55: =IS!I66 -> 2656.59 | Q55: =IS!J66 -> 2808.19 | R55: =IS!K66 -> 3158
B56: % of sales | D56: =D55/D35 -> 0.17331425 | E56: =E55/E35 -> 0.18318268 | F56: =F55/F35 -> 0.18719257 | G56: =G55/G35 -> 0.21422587 | H56: =H55/H35 -> 0.22381296 | I56: =I55/I35 -> 0.18533722 | J56: =J55/J35 -> 0.22106388 | K56: =K55/K35 -> 0.21375651 | ... R56: =R55/R35 -> 0.2207774
B58: Taxes(12/31 CYE) | D58: 2015 | E58: 2016 | F58: 2017 | G58: 2018 | H58: 2019 | I58: 2020 | J58: 2021 | K58: 2022 | L58: 2023 | M58: 2024 | N58: 2025E | O58: 2026E | P58: 2027E | Q58: 2028E | R58: 2029E
B60: Taxes | D60: =IS!B33 -> 102.448 | E60: =IS!C33 -> 119.348 | F60: =IS!D33 -> 201.336 | G60: =IS!E33 -> 231.449 | H60: =IS!F33 -> 251.797 | I60: =IS!G33 -> 230.437 | J60: =IS!H33 -> 358.547 | K60: =IS!I33 -> 477.771 | ... M60: =IS!K33 -> 761.461 | N60: =N55*N61 -> 730.41519 | O60: =O55*O61 -> 770.89635 | P60: =P55*P61 -> 792.55552 | Q60: =Q55*Q61 -> 837.78321 | R60: =R55*R61 -> 942.14401
B61: % taxes | D61: =IS!B33/IS!B32 -> 0.27801734 | E61: =IS!C33/IS!C32 -> 0.28232745 | F61: =IS!D33/IS!D32 -> 0.43768886 | G61: =IS!E33/IS!E32 -> 0.32359175 | H61: =IS!F33/IS!F32 -> 0.28058721 | I61: =IS!G33/IS!G32 -> 0.28124367 | J61: =IS!H33/IS!H32 -> 0.26880226 | K61: =IS!I33/IS!I32 -> 0.35853324 | ... M61: =IS!K33/IS!K32 -> 0.29558938 | N61: =AVERAGE($I$61:$M$61) -> 0.29833566 | O61: =AVERAGE($I$61:$M$61) -> 0.29833566 | P61: =AVERAGE($I$61:$M$61) -> 0.29833566 | Q61: =AVERAGE($I$61:$M$61) -> 0.29833566 | R61: =AVERAGE($I$61:$M$61) -> 0.29833566
B63: D&A | D63: 2015 | E63: 2016 | F63: 2017 | G63: 2018 | H63: 2019 | I63: 2020 | J63: 2021 | K63: 2022 | L63: 2023 | M63: 2024 | N63: 2025E | O63: 2026E | P63: 2027E | Q63: 2028E | R63: 2029E
B65: Company-operating stores | D65: =D77*D25 -> 54.001984 | E65: =E77*E25 -> 63.755121 | F65: =F77*F25 -> 75.05517 | G65: =G77*G25 -> 79.203218 | H65: =H77*H25 -> 101.77812 | I65: =I77*I25 -> 69.895652 | J65: =J77*J25 -> 101.1084 | K65: =K77*K25 -> 131.24817 | ... M65: =M77*M25 -> 190.16039 | N65: =N25*N77 -> 185.19479 | O65: =O25*O77 -> 197.98345 | P65: =P25*P77 -> 210.05119 | Q65: =Q25*Q77 -> 217.08232 | R65: =R25*R77 -> 235.97661
B66: % of total D&A | D66: =D65/D77 -> 0.7358923 | E66: =E65/E77 -> 0.72699318 | F66: =F65/F77 -> 0.69344639 | G66: =G65/G77 -> 0.64664134 | H66: =H65/H77 -> 0.62851997 | I66: =I65/I77 -> 0.37684066 | J66: =J65/J77 -> 0.45096208 | K66: =K65/K77 -> 0.44980197 | ... R66: =R65/R77 -> 0.42586824
B67: % of total Company-operating stores | D67: =D65/D23 -> 0.035613774 | E67: =E65/E23 -> 0.03740714 | F67: =F65/F23 -> 0.040856023 | G67: =G65/G23 -> 0.037248211 | H67: =H65/H23 -> 0.040693882 | I67: =I65/I23 -> 0.042136097 | J67: =J65/J23 -> 0.035835021 | K67: =K65/K23 -> 0.035976864 | ... M67: =M65/M23 -> 0.042172146 | N67: =AVERAGE(D67:M67) -> 0.038737912 | O67: =AVERAGE(E67:N67) -> 0.039050326 | P67: =AVERAGE(F67:O67) -> 0.039214645 | Q67: =AVERAGE(G67:P67) -> 0.039050507 | R67: =AVERAGE(H67:Q67) -> 0.039230737
B69: Direct to Consumer | D69: =D29*D77 -> 14.299821 | E69: =E29*E77 -> 16.95617 | F69: =F29*F77 -> 23.59803 | G69: =G29*G77 -> 31.99085 | H69: =H29*H77 -> 46.302394 | I69: =I29*I77 -> 96.241711 | J69: =J29*J77 -> 99.547681 | K69: =K29*K77 -> 133.10688 | ... M69: =M29*M77 -> 211.21444 | N69: =N77*N29 -> 205.69906 | O69: =O77*O29 -> 219.90366 | P69: =P77*P29 -> 233.3075 | Q69: =Q77*Q29 -> 241.1171 | R69: =R77*R29 -> 262.10332
B70: % of total D&A | E70: =E69/D69-1 -> 0.18576106 | F70: =F69/E69-1 -> 0.39170756 | G70: =G69/F69-1 -> 0.35565761 | H70: =H69/G69-1 -> 0.44736368 | I70: =I69/H69-1 -> 1.0785472 | J70: =J69/I69-1 -> 0.034350702 | K70: =K69/J69-1 -> 0.3371168 | L70: =L69/K69-1 -> 0.34820932 | M70: =M69/L69-1 -> 0.17697109 | N70: =AVERAGE($E$70:$M$70) -> 0.37285389 | O70: =AVERAGE($E$70:$M$70) -> 0.37285389 | P70: =AVERAGE($E$70:$M$70) -> 0.37285389 | Q70: =AVERAGE($E$70:$M$70) -> 0.37285389 | R70: =AVERAGE($E$70:$M$70) -> 0.37285389
B71: % of total Direct to Consumer | D71: =D69/D27 -> 0.035613774 | E71: =E69/E27 -> 0.03740714 | F71: =F69/F27 -> 0.040856023 | G71: =G69/G27 -> 0.037248211 | H71: =H69/H27 -> 0.040693882 | I71: =I69/I27 -> 0.042136097 | J71: =J69/J27 -> 0.035835021 | K71: =K69/K27 -> 0.035976864 | ... M71: =M69/M27 -> 0.042172146 | N71: =AVERAGE(D71:M71) -> 0.038737912 | O71: =AVERAGE(E71:N71) -> 0.039050326 | P71: =AVERAGE(F71:O71) -> 0.039214645 | Q71: =AVERAGE(G71:P71) -> 0.039050507 | R71: =AVERAGE(H71:Q71) -> 0.039230737
B73: Other | D73: =D77*D33 -> 5.0811952 | E73: =E77*E33 -> 6.9857086 | F73: =F77*F33 -> 9.5817997 | G73: =G77*G33 -> 11.289933 | H73: =H77*H33 -> 13.852482 | I73: =I77*I33 -> 19.340637 | J73: =J77*J33 -> 23.549916 | K73: =K77*K33 -> 27.435956 | ... R73: =R77*R33 -> 56.027167
B74: % of total D&A | E74: =E73/D73-1 -> 0.37481603 | F74: =F73/E73-1 -> 0.37162888 | G74: =G73/F73-1 -> 0.1782685 | H74: =H73/G73-1 -> 0.2269765 | I74: =I73/H73-1 -> 0.39618567 | J74: =J73/I73-1 -> 0.21763909 | K74: =K73/J73-1 -> 0.16501293 | L74: =L73/K73-1 -> 0.39818249 | ... R74: =R73/Q73-1 -> 0.087037473
B75: % of total Other | D75: =D73/D31 -> 0.035613774 | E75: =E73/E31 -> 0.03740714 | F75: =F73/F31 -> 0.040856023 | G75: =G73/G31 -> 0.037248211 | H75: =H73/H31 -> 0.040693882 | I75: =I73/I31 -> 0.042136097 | J75: =J73/J31 -> 0.035835021 | K75: =K73/K31 -> 0.035976864 | ... R75: =R73/R31 -> 0.038737912
B77: Total D&A | D77: =CF!B12 -> 73.383 | E77: =CF!C12 -> 87.697 | F77: =CF!D12 -> 108.235 | G77: =CF!E12 -> 122.484 | H77: =CF!F12 -> 161.933 | I77: =CF!G12 -> 185.478 | J77: =CF!H12 -> 224.206 | K77: =CF!I12 -> 291.791 | ... M77: =CF!K12 -> 446.524 | N77: =N35*N$78 -> 434.86406 | O77: =O35*O$78 -> 464.89369 | P77: =P35*P$78 -> 493.23047 | Q77: =Q35*Q$78 -> 509.74057 | R77: =R35*R$78 -> 554.1071
B78: % of sales | D78: =D77/D35 -> 0.035613774 | E78: =E77/E35 -> 0.03740714 | F78: =F77/F35 -> 0.040856023 | G78: =G77/G35 -> 0.037248211 | H78: =H77/H35 -> 0.040693882 | I78: =I77/I35 -> 0.042136097 | J78: =J77/J35 -> 0.035835021 | K78: =K77/K35 -> 0.035976864 | ... M78: =M77/M35 -> 0.042172146 | N78: =AVERAGE($D$78:$M$78) -> 0.038737912 | O78: =AVERAGE($D$78:$M$78) -> 0.038737912 | P78: =AVERAGE($D$78:$M$78) -> 0.038737912 | Q78: =AVERAGE($D$78:$M$78) -> 0.038737912 | R78: =AVERAGE($D$78:$M$78) -> 0.038737912
B79: % of CapEx | D79: =D77/D94 -> 0.51142612 | E79: =E77/E94 -> 0.58655885 | F79: =F77/F94 -> 0.6856218 | G79: =G77/G94 -> 0.54242783 | H79: =H77/H94 -> 0.57210438 | I79: =I77/I94 -> 0.80914905 | J79: =J77/J94 -> 0.56832665 | K79: =K77/K94 -> 0.45688218 | ... R79: =R77/R94 -> 0.70407509
B81: CapEx | D81: 2015 | E81: 2016 | F81: 2017 | G81: 2018 | H81: 2019 | I81: 2020 | J81: 2021 | K81: 2022 | L81: 2023 | M81: 2024 | N81: 2025E | O81: 2026E | P81: 2027E | Q81: 2028E | R81: 2029E
B82: Company-operating stores | D82: =D94*D25 -> 105.59098 | E82: =E94*E25 -> 108.69348 | F82: =F94*F25 -> 109.47022 | G82: =G94*G25 -> 146.01614 | H82: =H94*H25 -> 177.90132 | I82: =I94*I25 -> 86.381678 | J82: =J94*J25 -> 177.90544 | K82: =K94*K25 -> 287.26918 | ... R82: =R94*R25 -> 335.1583
B83: % of total CapEx | D83: =D82/D$94 -> 0.7358923 | E83: =E82/E94 -> 0.72699318 | F83: =F82/F94 -> 0.69344639 | G83: =G82/G94 -> 0.64664134 | H83: =H82/H94 -> 0.62851997 | I83: =I82/I94 -> 0.37684066 | J83: =J82/J94 -> 0.45096208 | K83: =K82/K94 -> 0.44980197 | L83: =L82/L94 -> 0.42586824 | ... R83: =R82/R94 -> 0.42586824
B84: % of total Company-operating stores | D84: =D82/D23 -> 0.069636204 | E84: =E82/E23 -> 0.063773891 | F84: =F82/F23 -> 0.059589737 | G84: =G82/G23 -> 0.068669433 | H84: =H82/H23 -> 0.07113017 | I84: =I82/I23 -> 0.05207458 | J84: =J82/J23 -> 0.063053564 | K84: =K82/K23 -> 0.078744292 | ... M84: =M82/M23 -> 0.065094805 | N84: =AVERAGE($D$84:$M$84) -> 0.06595332 | O84: =AVERAGE($D$84:$M$84) -> 0.06595332 | P84: =AVERAGE($D$84:$M$84) -> 0.06595332 | Q84: =AVERAGE($D$84:$M$84) -> 0.06595332 | R84: =AVERAGE($D$84:$M$84) -> 0.06595332
B86: Direct to Consumer | D86: =D94*D29 -> 27.960677 | E86: =E94*E29 -> 28.907876 | F86: =F94*F29 -> 34.418436 | G86: =G94*G29 -> 58.977154 | H86: =H94*H29 -> 80.933472 | I86: =I94*I29 -> 118.94188 | J86: =J94*J29 -> 175.15927 | K86: =K94*K29 -> 291.33742 | ... R86: =R94*R29 -> 372.26614
B87: % of total CapEx | D87: =D86/D$94 -> 0.19486558 | E87: =E86/E$94 -> 0.19334949 | F87: =F86/F$94 -> 0.21802587 | G87: =G86/G$94 -> 0.26118391 | H87: =H86/H$94 -> 0.2859355 | I87: =I86/I$94 -> 0.51888478 | J87: =J86/J$94 -> 0.44400097 | K87: =K86/K$94 -> 0.45617197 | ... R87: =R86/R$94 -> 0.47301924
B88: % of total Direct to Consumer | D88: =D86/D27 -> 0.069636204 | E88: =E86/E27 -> 0.063773891 | F88: =F86/F27 -> 0.059589737 | G88: =G86/G27 -> 0.068669433 | H88: =H86/H27 -> 0.07113017 | I88: =I86/I27 -> 0.05207458 | J88: =J86/J27 -> 0.063053564 | K88: =K86/K27 -> 0.078744292 | ... M88: =M86/M27 -> 0.065094805 | N88: =AVERAGE($D$88:$M$88) -> 0.06595332 | O88: =AVERAGE($D$88:$M$88) -> 0.06595332 | P88: =AVERAGE($D$88:$M$88) -> 0.06595332 | Q88: =AVERAGE($D$88:$M$88) -> 0.06595332 | R88: =AVERAGE($D$88:$M$88) -> 0.06595332
B90: Other | D90: =D94*D33 -> 9.9353454 | E90: =E94*E33 -> 11.909647 | F90: =F94*F33 -> 13.975343 | G90: =G94*G33 -> 20.813705 | H90: =H94*H33 -> 24.213208 | I90: =I94*I33 -> 23.902441 | J90: =J94*J33 -> 41.437289 | K90: =K94*K33 -> 60.050397 | ... R90: =R94*R33 -> 79.575556
B91: % of total CapEx | D91: =D90/D$94 -> 0.069242129 | E91: =E90/E$94 -> 0.079657327 | F91: =F90/F$94 -> 0.088527737 | G91: =G90/G$94 -> 0.092174756 | H91: =H90/H$94 -> 0.085544528 | I91: =I90/I$94 -> 0.10427456 | J91: =J90/J$94 -> 0.10503696 | K91: =K90/K$94 -> 0.094026054 | ... R91: =R90/R$94 -> 0.10111252
B92: % of total Other | D92: =D90/D31 -> 0.069636204 | E92: =E90/E31 -> 0.063773891 | F92: =F90/F31 -> 0.059589737 | G92: =G90/G31 -> 0.068669433 | H92: =H90/H31 -> 0.07113017 | I92: =I90/I31 -> 0.05207458 | J92: =J90/J31 -> 0.063053564 | K92: =K90/K31 -> 0.078744292 | ... M92: =M90/M31 -> 0.065094805 | N92: =AVERAGE($D$92:$M$92) -> 0.06595332 | O92: =AVERAGE($D$92:$M$92) -> 0.06595332 | P92: =AVERAGE($D$92:$M$92) -> 0.06595332 | Q92: =AVERAGE($D$92:$M$92) -> 0.06595332 | R92: =AVERAGE($D$92:$M$92) -> 0.06595332
B94: Total CapEx | D94: =-CF!B28 -> 143.487 | E94: =-CF!C28 -> 149.511 | F94: =-CF!D28 -> 157.864 | G94: =-CF!E28 -> 225.807 | H94: =-CF!F28 -> 283.048 | I94: =-CF!G28 -> 229.226 | J94: =-CF!H28 -> 394.502 | K94: =-CF!I28 -> 638.657 | ... M94: =-CF!K28 -> 689.232 | N94: =CF!G58 -> 757.291 | O94: =CF!H58 -> 806.813 | P94: =CF!I58 -> 827.477 | Q94: =CF!J58 -> 860.303 | R94: =CF!K58 -> 787
B95: % of sales | D95: =D94/D35 -> 0.069636204 | E95: =E94/E35 -> 0.063773891 | F95: =F94/F35 -> 0.059589737 | G95: =G94/G35 -> 0.068669433 | H95: =H94/H35 -> 0.07113017 | I95: =I94/I35 -> 0.05207458 | J95: =J94/J35 -> 0.063053564 | K95: =K94/K35 -> 0.078744292 | ... R95: =R94/R35 -> 0.055019575
B97: Net Working Capital | D97: 2015 | E97: 2016 | F97: 2017 | G97: 2018 | H97: 2019 | I97: 2020 | J97: 2021 | K97: 2022 | L97: 2023 | M97: 2024 | N97: 2025E | O97: 2026E | P97: 2027E | Q97: 2028E | R97: 2029E
B98: Company-operating stores | D98: =D100*D110 -> 43.964413 | E98: =E100*E110 -> -0.43837689 | F98: =F100*F110 -> -72.553909 | G98: =G100*G110 -> -72.989641 | H98: =H100*H110 -> 121.9775 | I98: =I100*I110 -> 17.918397 | J98: =J100*J110 -> -58.233184 | K98: =K100*K110 -> 268.52818 | ... M98: =M100*M110 -> 22.100432 | N98: =N100*N$110 -> 92.104514 | O98: =O100*O$110 -> 98.46481 | P98: =P100*P$110 -> 104.46656 | Q98: =Q100*Q$110 -> 107.96341 | R98: =R100*R$110 -> 117.36027
B99: % of Company-operating stores | D99: =D98/D23 -> 0.028994095 | E99: =E98/E23 -> -0.00025720955 | F99: =F98/F23 -> -0.03949447 | G99: =G98/G23 -> -0.034326049 | H99: =H98/H23 -> 0.048770184 | I99: =I98/I23 -> 0.010801978 | J99: =J98/J23 -> -0.020639109 | K99: =K98/K23 -> 0.073607136 | ... R99: =R98/R23 -> 0.019265858
B100: % of total Company-operating stores | D100: =D25 -> 0.7358923 | E100: =E25 -> 0.72699318 | F100: =F25 -> 0.69344639 | G100: =G25 -> 0.64664134 | H100: =H25 -> 0.62851997 | I100: =I25 -> 0.37684066 | J100: =J25 -> 0.45096208 | K100: =K25 -> 0.44980197 | ... M100: =M25 -> 0.42586824 | N100: =AVERAGE($I$100:$M$100) -> 0.42586824 | O100: =AVERAGE($I$100:$M$100) -> 0.42586824 | P100: =AVERAGE($I$100:$M$100) -> 0.42586824 | Q100: =AVERAGE($I$100:$M$100) -> 0.42586824 | R100: =AVERAGE($I$100:$M$100) -> 0.42586824
B102: Direct to Consumer | D102: =D104*D110 -> 11.641854 | E102: =E104*E110 -> -0.11658974 | F102: =F104*F110 -> -22.811611 | G102: =G104*G110 -> -29.481133 | H102: =H104*H110 -> 55.491789 | I102: =I104*I110 -> 24.672452 | J102: =J104*J110 -> -57.334289 | K102: =K104*K110 -> 272.33102 | ... M102: =M104*M110 -> 24.547333 | N102: =N104*N$110 -> 102.30208 | O102: =O104*O$110 -> 109.36657 | P102: =P104*P$110 -> 116.03282 | Q102: =Q104*Q$110 -> 119.91683 | R102: =R104*R$110 -> 130.35409
B103: % of Direct to Consumer | D103: =D102/D27 -> 0.028994095 | E103: =E102/E27 -> -0.00025720955 | F103: =F102/F27 -> -0.03949447 | G103: =G102/G27 -> -0.034326049 | H103: =H102/H27 -> 0.048770184 | I103: =I102/I27 -> 0.010801978 | J103: =J102/J27 -> -0.020639109 | K103: =K102/K27 -> 0.073607136 | ... R103: =R102/R27 -> 0.019265858
B104: % of total Direct to Consumer | D104: =D29 -> 0.19486558 | E104: =E29 -> 0.19334949 | F104: =F29 -> 0.21802587 | G104: =G29 -> 0.26118391 | H104: =H29 -> 0.2859355 | I104: =I29 -> 0.51888478 | J104: =J29 -> 0.44400097 | K104: =K29 -> 0.45617197 | ... M104: =M29 -> 0.47301924 | N104: =AVERAGE($I$104:$M$104) -> 0.47301924 | O104: =AVERAGE($I$104:$M$104) -> 0.47301924 | P104: =AVERAGE($I$104:$M$104) -> 0.47301924 | Q104: =AVERAGE($I$104:$M$104) -> 0.47301924 | R104: =AVERAGE($I$104:$M$104) -> 0.47301924
B106: Other | D106: =D110*D108 -> 4.1367325 | E106: =E110*E108 -> -0.048033368 | F106: =F110*F108 -> -9.2624801 | G106: =G110*G108 -> -10.404226 | H106: =H110*H108 -> 16.601712 | I106: =I110*I108 -> 4.9581511 | J106: =J110*J108 -> -13.563527 | K106: =K110*K108 -> 56.132802 | ... R106: =R110*R108 -> 27.864472
B107: % of Other | D107: =D106/D31 -> 0.028994095 | E107: =E106/E31 -> -0.00025720955 | F107: =F106/F31 -> -0.03949447 | G107: =G106/G31 -> -0.034326049 | H107: =H106/H31 -> 0.048770184 | I107: =I106/I31 -> 0.010801978 | J107: =J106/J31 -> -0.020639109 | K107: =K106/K31 -> 0.073607136 | ... R107: =R106/R31 -> 0.019265858
B108: % of total Other | D108: =D53 -> 0.069242129 | E108: =E53 -> 0.079657327 | F108: =F53 -> 0.088527737 | G108: =G53 -> 0.092174756 | H108: =H53 -> 0.085544528 | I108: =I53 -> 0.10427456 | J108: =J53 -> 0.10503696 | K108: =K53 -> 0.094026054 | ... M108: =M53 -> 0.10111252 | N108: =AVERAGE($I$108:$M$108) -> 0.10111252 | O108: =AVERAGE($I$108:$M$108) -> 0.10111252 | P108: =AVERAGE($I$108:$M$108) -> 0.10111252 | Q108: =AVERAGE($I$108:$M$108) -> 0.10111252 | R108: =AVERAGE($I$108:$M$108) -> 0.10111252
B110: Total Change in NWC | D110: =-CF!B19 -> 59.743 | E110: =-CF!C19 -> -0.603 | F110: =-CF!D19 -> -104.628 | G110: =-CF!E19 -> -112.875 | H110: =-CF!F19 -> 194.071 | I110: =-CF!G19 -> 47.549 | J110: =-CF!H19 -> -129.131 | K110: =-CF!I19 -> 596.992 | ... M110: =-CF!K19 -> 51.895 | N110: =N35*N$111 -> 216.27467 | O110: =O35*O$111 -> 231.20957 | P110: =P35*P$111 -> 245.30254 | Q110: =Q35*Q$111 -> 253.51365 | R110: =R35*R$111 -> 275.57884
B111: % of sales | D111: =D110/D35 -> 0.028994095 | E111: =E110/E35 -> -0.00025720955 | F111: =F110/F35 -> -0.03949447 | G111: =G110/G35 -> -0.034326049 | H111: =H110/H35 -> 0.048770184 | I111: =I110/I35 -> 0.010801978 | J111: =J110/J35 -> -0.020639109 | K111: =K110/K35 -> 0.073607136 | ... M111: =M110/M35 -> 0.004901245 | N111: =AVERAGE($K$111:$M$111) -> 0.019265858 | O111: =AVERAGE($K$111:$M$111) -> 0.019265858 | P111: =AVERAGE($K$111:$M$111) -> 0.019265858 | Q111: =AVERAGE($K$111:$M$111) -> 0.019265858 | R111: =AVERAGE($K$111:$M$111) -> 0.019265858
B112: % of change in sales | E112: =E110/(E35-D35) -> -0.0021242193 | F112: =F110/(F35-E35) -> -0.34328011 | G112: =G110/(G35-F35) -> -0.17660505 | H112: =H110/(H35-G35) -> 0.28086463 | I112: =I110/(I35-H35) -> 0.11251991 | J112: =J110/(J35-I35) -> -0.069622232 | K112: =K110/(K35-J35) -> 0.32201935 | L112: =L110/(L35-K35) -> -0.1320442 | ... R112: =R110/(R35-Q35) -> 0.24061716
N113: 1 | O113: 2 | P113: 3 | Q113: 4 | R113: 5
B114: DCF | D114: 2015 | E114: 2016 | F114: 2017 | G114: 2018 | H114: 2019 | I114: 2020 | J114: 2021 | K114: 2022 | L114: 2023 | M114: 2024 | N114: 2025 | O114: 2026 | P114: 2027 | Q114: 2028 | R114: 2029
B115: Revenue | D115: =D35 -> 2060.523 | E115: =E35 -> 2344.392 | F115: =F35 -> 2649.181 | G115: =G35 -> 3288.319 | H115: =H35 -> 3979.296 | I115: =I35 -> 4401.879 | J115: =J35 -> 6256.617 | K115: =K35 -> 8110.518 | ... M115: =M35 -> 10588.126 | N115: =M115*(1+N116) -> 11225.8 | O115: =N115*(1+O116) -> 12001 | P115: =O115*(1+P116) -> 12961.08 | Q115: =P115*(1+Q116) -> 13963.525 | R115: =Q115*(1+R116) -> 14801.337
B116: % growth | D116: -- | E116: =E115/D115-1 -> 0.13776551 | F116: =F115/E115-1 -> 0.13000769 | G116: =G115/F115-1 -> 0.24125871 | H116: =H115/G115-1 -> 0.21013077 | I116: =I115/H115-1 -> 0.10619542 | J116: =J115/I115-1 -> 0.42135143 | K116: =K115/J115-1 -> 0.29631045 | L116: =L115/K115-1 -> 0.18602511 | M116: =M115/L115-1 -> 0.10071941 | N116: =N36 -> 0.060225388 | O116: =OFFSET(O116,$D$11,0) -> 0.069055212 | P116: =OFFSET(P116,$D$11,0) -> 0.08 | Q116: =OFFSET(Q116,$D$11,0) -> 0.077342721 | R116: =OFFSET(R116,$D$11,0) -> 0.06
B117: Conservative | N117: =N118 -> 0.060225388 | O117: =O118*$H$11 -> 0.05524417 | P117: =P118*$H$11 -> 0.064 | Q117: =Q118*$H$11 -> 0.061874177 | R117: =R118*$H$11 -> 0.048 | S117: =IF($D$15=0,$H$13,O118*$H$11) -> 0.05524417 | T117: =IF($D$15=0,$H$13,P118*$H$11) -> 0.064 | U117: =IF($D$15=0,$H$13,Q118*$H$11) -> 0.061874177 | V117: =IF($D$15=0,$H$13,R118*$H$11) -> 0.048
B118: Base | N118: =N36 -> 0.060225388 | O118: =O36 -> 0.069055212 | P118: =L11 -> 0.08 | Q118: =P118+(($R$124-$O$124)/($R$114-$P$114)) -> 0.077342721 | R118: =L12 -> 0.06 | S118: =IF($D$15=0,$L$14,O39) -> 0.069055212 | T118: =IF($D$15=0,$L$14,L11) -> 0.08 | U118: =IF($D$15=0,$L$14,P118+(($R$118-$O$118)/($R$114-P114))) -> 0.075472394 | V118: =IF($D$15=0,$L$14,L12) -> 0.06
B119: Optimisitic | N119: =N118 -> 0.060225388 | O119: =O118*$P$11 -> 0.082866255 | P119: =P118*$P$11 -> 0.096 | Q119: =Q118*$P$11 -> 0.092811266 | R119: =R118*$P$11 -> 0.072
B121: EBIT | D121: =D55 -> 357.118 | E121: =E55 -> 429.452 | F121: =F55 -> 495.907 | G121: =G55 -> 704.443 | H121: =H55 -> 890.618 | I121: =I55 -> 815.832 | J121: =J55 -> 1383.112 | K121: =K55 -> 1733.676 | ... M121: =M55 -> 2499.777 | N121: =N115*N122 -> 2448.3 | O121: =O115*O122 -> 2583.99 | P121: =P115*P122 -> 2767.7484 | Q121: =Q115*Q122 -> 2944.7086 | R121: =R115*R122 -> 3108.2807
B122: % of sales | D122: =D121/D35 -> 0.17331425 | E122: =E121/E35 -> 0.18318268 | F122: =F121/F35 -> 0.18719257 | G122: =G121/G35 -> 0.21422587 | H122: =H121/H35 -> 0.22381296 | I122: =I121/I35 -> 0.18533722 | J122: =J121/J35 -> 0.22106388 | K122: =K121/K35 -> 0.21375651 | ... M122: =M121/M35 -> 0.23609249 | N122: =OFFSET(N122,$D$12,0) -> 0.21809581 | O122: =OFFSET(O122,$D$12,0) -> 0.21531456 | P122: =OFFSET(P122,$D$12,0) -> 0.21354304 | Q122: =OFFSET(Q122,$D$12,0) -> 0.21088576 | R122: =OFFSET(R122,$D$12,0) -> 0.21
B123: Conservative | N123: =N124 -> 0.21809581 | O123: =N123*$H$12 -> 0.19628623 | P123: =O123*$H$12 -> 0.17665761 | Q123: =P123*$H$12 -> 0.15899185 | R123: =Q123*$H$12 -> 0.14309266
B124: Base | N124: =N56 -> 0.21809581 | O124: =O56 -> 0.21531456 | P124: =O124+(($R$124-$O$124)/($R$114-O114)) -> 0.21354304 | Q124: =P124+(($R$124-$O$124)/($R$114-P114)) -> 0.21088576 | R124: =L13 -> 0.21
B125: Optimisitic | N125: =N124 -> 0.21809581 | O125: =O124*$P$12 -> 0.23684601 | P125: =P124*$P$12 -> 0.23489734 | Q125: =Q124*$P$12 -> 0.23197434 | R125: =R124*$P$12 -> 0.231
B127: Taxes | D127: =D60 -> 102.448 | E127: =E60 -> 119.348 | F127: =F60 -> 201.336 | G127: =G60 -> 231.449 | H127: =H60 -> 251.797 | I127: =I60 -> 230.437 | J127: =J60 -> 358.547 | K127: =K60 -> 477.771 | ... M127: =M60 -> 761.461 | N127: =N128*N121 -> 730.41519 | O127: =O128*O121 -> 779.72946 | P127: =P128*P121 -> 853.41976 | Q127: =Q128*Q121 -> 878.42616 | R127: =R128*R121 -> 933.93277
B128: % of EBIT | D128: =D61 -> 0.27801734 | E128: =E61 -> 0.28232745 | F128: =F61 -> 0.43768886 | G128: =G61 -> 0.32359175 | H128: =H61 -> 0.28058721 | I128: =I61 -> 0.28124367 | J128: =J61 -> 0.26880226 | K128: =K61 -> 0.35853324 | ... M128: =M61 -> 0.29558938 | N128: =AVERAGE(I128:M128) -> 0.29833566 | O128: =AVERAGE(J128:N128) -> 0.30175405 | P128: =AVERAGE(K128:O128) -> 0.30834441 | Q128: =AVERAGE(L128:P128) -> 0.29830665 | R128: =AVERAGE(M128:Q128) -> 0.30046603
B130: EBIAT | N130: =N121-N127 -> 1717.8848 | O130: =O121-O127 -> 1804.2605 | P130: =P121-P127 -> 1914.3286 | Q130: =Q121-Q127 -> 2066.2825 | R130: =R121-R127 -> 2174.3479
...

Sheet Consolidated
B2: Consolidated DCF
A4: x | B4: Assumptions
B5: WACC | D5: =WACC -> 0.084126282
B6: TGR | D6: =TGR -> 0.025
A9: x | B9: DCF | D9: 2015 | E9: 2016 | F9: 2017 | G9: 2018 | H9: 2019 | I9: 2020 | J9: 2021 | K9: 2022 | L9: 2023 | M9: 2024 | N9: 2025 | O9: 2026 | P9: 2027 | Q9: 2028 | R9: 2029
A11: x | B11: Revenue | D11: ='Company-operated store DCF'!D11+'Direct to Consumer DCF'!D11+'Other DCF'!D11 -> 2060.523 | E11: ='Company-operated store DCF'!E11+'Direct to Consumer DCF'!E11+'Other DCF'!E11 -> 2344.392 | F11: ='Company-operated store DCF'!F11+'Direct to Consumer DCF'!F11+'Other DCF'!F11 -> 2649.181 | G11: ='Company-operated store DCF'!G11+'Direct to Consumer DCF'!G11+'Other DCF'!G11 -> 3288.319 | H11: ='Company-operated store DCF'!H11+'Direct to Consumer DCF'!H11+'Other DCF'!H11 -> 3979.296 | I11: ='Company-operated store DCF'!I11+'Direct to Consumer DCF'!I11+'Other DCF'!I11 -> 4401.879 | J11: ='Company-operated store DCF'!J11+'Direct to Consumer DCF'!J11+'Other DCF'!J11 -> 6256.617 | K11: ='Company-operated store DCF'!K11+'Direct to Consumer DCF'!K11+'Other DCF'!K11 -> 8110.518 | ... R11: ='Company-operated store DCF'!R11+'Direct to Consumer DCF'!R11+'Other DCF'!R11 -> 14801.337
B12: % growth | E12: =E11/D11-1 -> 0.13776551 | F12: =F11/E11-1 -> 0.13000769 | G12: =G11/F11-1 -> 0.24125871 | H12: =H11/G11-1 -> 0.21013077 | I12: =I11/H11-1 -> 0.10619542 | J12: =J11/I11-1 -> 0.42135143 | K12: =K11/J11-1 -> 0.29631045 | L12: =L11/K11-1 -> 0.18602511 | M12: =M11/L11-1 -> 0.10071941 | N12: =OFFSET(N12,DCF!$D$11,0) -> 0.060225388 | O12: =OFFSET(O12,DCF!$D$11,0) -> 0.069055212 | P12: =OFFSET(P12,DCF!$D$11,0) -> 0.14501595 | Q12: =OFFSET(Q12,DCF!$D$11,0) -> 0.30453349 | R12: =OFFSET(R12,DCF!$D$11,0) -> 0.63952032
B13: Conservative | N13: 0.060225388 | O13: 0.062149691 | P13: 0.13051435 | Q13: 0.27408014 | R13: 0.57556829
B14: Base | N14: 0.060225388 | O14: 0.069055212 | P14: 0.14501595 | Q14: 0.30453349 | R14: 0.63952032
B15: Optimisitic | N15: 0.060225388 | O15: 0.082866255 | P15: 0.17401913 | Q15: 0.36544018 | R15: 0.76742438
B17: EBIT | D17: ='Company-operated store DCF'!D17+'Direct to Consumer DCF'!D17+'Other DCF'!D17 -> 357.118 | E17: ='Company-operated store DCF'!E17+'Direct to Consumer DCF'!E17+'Other DCF'!E17 -> 429.452 | F17: ='Company-operated store DCF'!F17+'Direct to Consumer DCF'!F17+'Other DCF'!F17 -> 495.907 | G17: ='Company-operated store DCF'!G17+'Direct to Consumer DCF'!G17+'Other DCF'!G17 -> 704.443 | H17: ='Company-operated store DCF'!H17+'Direct to Consumer DCF'!H17+'Other DCF'!H17 -> 890.618 | I17: ='Company-operated store DCF'!I17+'Direct to Consumer DCF'!I17+'Other DCF'!I17 -> 815.832 | J17: ='Company-operated store DCF'!J17+'Direct to Consumer DCF'!J17+'Other DCF'!J17 -> 1383.112 | K17: ='Company-operated store DCF'!K17+'Direct to Consumer DCF'!K17+'Other DCF'!K17 -> 1733.676 | ... R17: ='Company-operated store DCF'!R17+'Direct to Consumer DCF'!R17+'Other DCF'!R17 -> 3108.2807
B18: % of sales | E18: =E17/E11 -> 0.18318268 | F18: =F17/F11 -> 0.18719257 | G18: =G17/G11 -> 0.21422587 | H18: =H17/H11 -> 0.22381296 | I18: =I17/I11 -> 0.18533722 | J18: =J17/J11 -> 0.22106388 | K18: =K17/K11 -> 0.21375651 | L18: =L17/L11 -> 0.22950205 | M18: =M17/M11 -> 0.23609249 | N18: =OFFSET(N18,DCF!$D$11,0) -> 0.21809581 | O18: =OFFSET(O18,DCF!$D$11,0) -> 0.20282911 | P18: =OFFSET(P18,DCF!$D$11,0) -> 0.18863107 | Q18: =OFFSET(Q18,DCF!$D$11,0) -> 0.1754269 | R18: =OFFSET(R18,DCF!$D$11,0) -> 0.16314701
B19: Conservative | N19: 0.21809581 | O19: 0.19628623 | P19: 0.17665761 | Q19: 0.15899185 | R19: 0.14309266
B20: Base | N20: 0.21809581 | O20: 0.20282911 | P20: 0.18863107 | Q20: 0.1754269 | R20: 0.16314701
B21: Optimisitic | N21: 0.21809581 | O21: 0.20688569 | P21: 0.19240369 | Q21: 0.17893543 | R21: 0.16640995
B23: Taxes | D23: ='Company-operated store DCF'!D23+'Direct to Consumer DCF'!D23+'Other DCF'!D23 -> 99.284997 | E23: ='Company-operated store DCF'!E23+'Direct to Consumer DCF'!E23+'Other DCF'!E23 -> 121.24609 | F23: ='Company-operated store DCF'!F23+'Direct to Consumer DCF'!F23+'Other DCF'!F23 -> 217.05297 | G23: ='Company-operated store DCF'!G23+'Direct to Consumer DCF'!G23+'Other DCF'!G23 -> 227.95194 | H23: ='Company-operated store DCF'!H23+'Direct to Consumer DCF'!H23+'Other DCF'!H23 -> 249.89602 | I23: ='Company-operated store DCF'!I23+'Direct to Consumer DCF'!I23+'Other DCF'!I23 -> 229.44758 | J23: ='Company-operated store DCF'!J23+'Direct to Consumer DCF'!J23+'Other DCF'!J23 -> 371.78363 | K23: ='Company-operated store DCF'!K23+'Direct to Consumer DCF'!K23+'Other DCF'!K23 -> 621.58048 | ... R23: ='Company-operated store DCF'!R23+'Direct to Consumer DCF'!R23+'Other DCF'!R23 -> 927.31097
B24: % tax rate | D24: =DCF!D61 -> 0.27801734 | E24: =DCF!E61 -> 0.28232745 | F24: =DCF!F61 -> 0.43768886 | G24: =DCF!G61 -> 0.32359175 | H24: =DCF!H61 -> 0.28058721 | I24: =DCF!I61 -> 0.28124367 | J24: =DCF!J61 -> 0.26880226 | K24: =DCF!K61 -> 0.35853324 | ... R24: =DCF!R61 -> 0.29833566
B26: EBIAT | D26: =D17-D23 -> 257.833 | E26: =E17-E23 -> 308.20591 | F26: =F17-F23 -> 278.85403 | G26: =G17-G23 -> 476.49106 | H26: =H17-H23 -> 640.72198 | I26: =I17-I23 -> 586.38442 | J26: =J17-J23 -> 1011.3284 | K26: =K17-K23 -> 1112.0955 | ... R26: =R17-R23 -> 2180.9697
B28: D&A | D28: ='Company-operated store DCF'!D28+'Direct to Consumer DCF'!D28+'Other DCF'!D28 -> 73.383 | E28: ='Company-operated store DCF'!E28+'Direct to Consumer DCF'!E28+'Other DCF'!E28 -> 87.697 | F28: ='Company-operated store DCF'!F28+'Direct to Consumer DCF'!F28+'Other DCF'!F28 -> 108.235 | G28: ='Company-operated store DCF'!G28+'Direct to Consumer DCF'!G28+'Other DCF'!G28 -> 122.484 | H28: ='Company-operated store DCF'!H28+'Direct to Consumer DCF'!H28+'Other DCF'!H28 -> 161.933 | I28: ='Company-operated store DCF'!I28+'Direct to Consumer DCF'!I28+'Other DCF'!I28 -> 185.478 | J28: ='Company-operated store DCF'!J28+'Direct to Consumer DCF'!J28+'Other DCF'!J28 -> 224.206 | K28: ='Company-operated store DCF'!K28+'Direct to Consumer DCF'!K28+'Other DCF'!K28 -> 291.791 | ... R28: ='Company-operated store DCF'!R28+'Direct to Consumer DCF'!R28+'Other DCF'!R28 -> 554.1071
B29: % of sales | D29: =D28/D11 -> 0.035613774 | E29: =E28/E11 -> 0.03740714 | F29: =F28/F11 -> 0.040856023 | G29: =G28/G11 -> 0.037248211 | H29: =H28/H11 -> 0.040693882 | I29: =I28/I11 -> 0.042136097 | J29: =J28/J11 -> 0.035835021 | K29: =K28/K11 -> 0.035976864 | ... R29: =R28/R11 -> 0.037436288
B31: CapEx | D31: ='Company-operated store DCF'!D31+'Direct to Consumer DCF'!D31+'Other DCF'!D31 -> 143.487 | E31: ='Company-operated store DCF'!E31+'Direct to Consumer DCF'!E31+'Other DCF'!E31 -> 149.511 | F31: ='Company-operated store DCF'!F31+'Direct to Consumer DCF'!F31+'Other DCF'!F31 -> 157.864 | G31: ='Company-operated store DCF'!G31+'Direct to Consumer DCF'!G31+'Other DCF'!G31 -> 225.807 | H31: ='Company-operated store DCF'!H31+'Direct to Consumer DCF'!H31+'Other DCF'!H31 -> 283.048 | I31: ='Company-operated store DCF'!I31+'Direct to Consumer DCF'!I31+'Other DCF'!I31 -> 229.226 | J31: ='Company-operated store DCF'!J31+'Direct to Consumer DCF'!J31+'Other DCF'!J31 -> 394.502 | K31: ='Company-operated store DCF'!K31+'Direct to Consumer DCF'!K31+'Other DCF'!K31 -> 638.657 | ... R31: ='Company-operated store DCF'!R31+'Direct to Consumer DCF'!R31+'Other DCF'!R31 -> 787
B32: % of sales | D32: =D31/D11 -> 0.069636204 | E32: =E31/E11 -> 0.063773891 | F32: =F31/F11 -> 0.059589737 | G32: =G31/G11 -> 0.068669433 | H32: =H31/H11 -> 0.07113017 | I32: =I31/I11 -> 0.05207458 | J32: =J31/J11 -> 0.063053564 | K32: =K31/K11 -> 0.078744292 | ... R32: =R31/R11 -> 0.053170873
B34: Change in NWC | D34: ='Company-operated store DCF'!D34+'Direct to Consumer DCF'!D34+'Other DCF'!D34 -> 59.743 | E34: ='Company-operated store DCF'!E34+'Direct to Consumer DCF'!E34+'Other DCF'!E34 -> -0.603 | F34: ='Company-operated store DCF'!F34+'Direct to Consumer DCF'!F34+'Other DCF'!F34 -> -104.628 | G34: ='Company-operated store DCF'!G34+'Direct to Consumer DCF'!G34+'Other DCF'!G34 -> -112.875 | H34: ='Company-operated store DCF'!H34+'Direct to Consumer DCF'!H34+'Other DCF'!H34 -> 194.071 | I34: ='Company-operated store DCF'!I34+'Direct to Consumer DCF'!I34+'Other DCF'!I34 -> 47.549 | J34: ='Company-operated store DCF'!J34+'Direct to Consumer DCF'!J34+'Other DCF'!J34 -> -129.131 | K34: ='Company-operated store DCF'!K34+'Direct to Consumer DCF'!K34+'Other DCF'!K34 -> 596.992 | ... R34: ='Company-operated store DCF'!R34+'Direct to Consumer DCF'!R34+'Other DCF'!R34 -> 275.57884
B35: % of sales | D35: =D34/D11 -> 0.028994095 | E35: =E34/E11 -> -0.00025720955 | F35: =F34/F11 -> -0.03949447 | G35: =G34/G11 -> -0.034326049 | H35: =H34/H11 -> 0.048770184 | I35: =I34/I11 -> 0.010801978 | J35: =J34/J11 -> -0.020639109 | K35: =K34/K11 -> 0.073607136 | ... R35: =R34/R11 -> 0.01861851
B37: Unlevered FCF | D37: =D26+D28-D31-D34 -> 127.986 | E37: =E26+E28-E31-E34 -> 246.99491 | F37: =F26+F28-F31-F34 -> 333.85303 | G37: =G26+G28-G31-G34 -> 486.04306 | H37: =H26+H28-H31-H34 -> 325.53598 | I37: =I26+I28-I31-I34 -> 495.08742 | J37: =J26+J28-J31-J34 -> 970.16337 | K37: =K26+K28-K31-K34 -> 168.23752 | ... R37: =R26+R28-R31-R34 -> 1672.498
B38: PV FCF | N38: =(N37*N40)/(1+D5)^N41 -> 49.050022 | O38: =O37/(1+$D$5)^O41 -> 1188.8815 | P38: =P37/(1+$D$5)^P41 -> 1204.9802 | Q38: =Q37/(1+$D$5)^Q41 -> 1192.7592 | R38: =R37/(1+$D$5)^R41 -> 1258.5058
B40: Period | N40: =DCF!N144 -> 0.041666667
B41: Discount Period | N41: =DCF!N145 -> 0.020833333 | O41: =DCF!O145 -> 0.52083333 | P41: =DCF!P145 -> 1.5208333 | Q41: =DCF!Q145 -> 2.5208333 | R41: =DCF!R145 -> 3.5208333
B43: Terminal Value | R43: =(R37*(1+D6))/(D5-D6) -> 28994.051
B44: PV TV | R44: =R43/(1+WACC)^R41 -> 21817.175
B46: Enterprise Value | R46: =SUM(N38:R38)+R44 -> 26711.352
B47: (+) Cash | R47: =DCF!R150 -> 1984.336
B48: (-) Debt | R48: =DCF!R151 -> 1575.8
B49: Equity Value | R49: =R46+R47-R48 -> 27119.888
B51: Diluted Shares | R51: =Shares!E14 -> 116.37023
B52: Implied Stock Price | R52: =R49/R51 -> 233.04833

Sheet Company-operated store DCF
B2: Company-operated stores DCF
A4: x | B4: Assumptions
B5: WACC | D5: =WACC -> 0.084126282
B6: TGR | D6: =TGR -> 0.025
A9: x | B9: DCF | D9: 2015 | E9: 2016 | F9: 2017 | G9: 2018 | H9: 2019 | I9: 2020 | J9: 2021 | K9: 2022 | L9: 2023 | M9: 2024 | N9: 2025 | O9: 2026 | P9: 2027 | Q9: 2028 | R9: 2029
A11: x | B11: Revenue | D11: =DCF!D23 -> 1516.323 | E11: =DCF!E23 -> 1704.357 | F11: =DCF!F23 -> 1837.065 | G11: =DCF!G23 -> 2126.363 | H11: =DCF!H23 -> 2501.067 | I11: =DCF!I23 -> 1658.807 | J11: =DCF!J23 -> 2821.497 | K11: =DCF!K23 -> 3648.127 | ... M11: =DCF!M23 -> 4509.1466 | N11: =M11*(1+N12) -> 4780.7117 | O11: =N11*(1+O12) -> 5110.8447 | P11: =O11*(1+P12) -> 5519.7123 | Q11: =P11*(1+Q12) -> 5946.6219 | R11: =Q11*(1+R12) -> 6303.4192
B12: % growth | E12: =DCF!E24 -> 0.12400656 | F12: =DCF!F24 -> 0.077863969 | G12: =DCF!G24 -> 0.15747837 | H12: =DCF!H24 -> 0.17621827 | I12: =DCF!I24 -> -0.33676027 | J12: =DCF!J24 -> 0.7009194 | K12: =DCF!K24 -> 0.29297568 | L12: =DCF!L24 -> 0.12291731 | M12: =DCF!M24 -> 0.10071941 | N12: =OFFSET(N12,DCF!$D$11,0) -> 0.060225388 | O12: =OFFSET(O12,DCF!$D$11,0) -> 0.069055212 | P12: =OFFSET(P12,DCF!$D$11,0) -> 0.08 | Q12: =OFFSET(Q12,DCF!$D$11,0) -> 0.077342721 | R12: =OFFSET(R12,DCF!$D$11,0) -> 0.06
B13: Conservative | N13: =DCF!N117 -> 0.060225388 | O13: =DCF!O117 -> 0.05524417 | P13: =DCF!P117 -> 0.064 | Q13: =DCF!Q117 -> 0.061874177 | R13: =DCF!R117 -> 0.048
B14: Base | N14: =DCF!N118 -> 0.060225388 | O14: =DCF!O118 -> 0.069055212 | P14: =DCF!P118 -> 0.08 | Q14: =DCF!Q118 -> 0.077342721 | R14: =DCF!R118 -> 0.06
B15: Optimisitic | N15: =DCF!N119 -> 0.060225388 | O15: =DCF!O119 -> 0.082866255 | P15: =DCF!P119 -> 0.096 | Q15: =DCF!Q119 -> 0.092811266 | R15: =DCF!R119 -> 0.072
B17: EBIT | D17: =DCF!D43 -> 262.80038 | E17: =DCF!E43 -> 312.20868 | F17: =DCF!F43 -> 343.88492 | G17: =DCF!G43 -> 455.52196 | H17: =DCF!H43 -> 559.7712 | I17: =DCF!I43 -> 307.43867 | J17: =DCF!J43 -> 623.73106 | K17: =DCF!K43 -> 779.81089 | ... M17: =DCF!M43 -> 1064.5756 | N17: =N11*N18 -> 1042.6532 | O17: =O11*O18 -> 1100.4393 | P17: =P11*P18 -> 1178.6961 | Q17: =Q11*Q18 -> 1254.0579 | R17: =R11*R18 -> 1323.718
B18: % of sales | E18: =DCF!E44 -> 0.18318268 | F18: =DCF!F44 -> 0.18719257 | G18: =DCF!G44 -> 0.21422587 | H18: =DCF!H44 -> 0.22381296 | I18: =DCF!I44 -> 0.18533722 | J18: =DCF!J44 -> 0.22106388 | K18: =DCF!K44 -> 0.21375651 | L18: =DCF!L44 -> 0.22950205 | M18: =DCF!M44 -> 0.23609249 | N18: =OFFSET(N18,DCF!$D$12,0) -> 0.21809581 | O18: =OFFSET(O18,DCF!$D$12,0) -> 0.21531456 | P18: =OFFSET(P18,DCF!$D$12,0) -> 0.21354304 | Q18: =OFFSET(Q18,DCF!$D$12,0) -> 0.21088576 | R18: =OFFSET(R18,DCF!$D$12,0) -> 0.21
B19: Conservative | N19: =DCF!N123 -> 0.21809581 | O19: =DCF!O123 -> 0.19628623 | P19: =DCF!P123 -> 0.17665761 | Q19: =DCF!Q123 -> 0.15899185 | R19: =DCF!R123 -> 0.14309266
B20: Base | N20: =DCF!N124 -> 0.21809581 | O20: =DCF!O124 -> 0.21531456 | P20: =DCF!P124 -> 0.21354304 | Q20: =DCF!Q124 -> 0.21088576 | R20: =DCF!R124 -> 0.21
B21: Optimisitic | N21: =DCF!N125 -> 0.21809581 | O21: =DCF!O125 -> 0.23684601 | P21: =DCF!P125 -> 0.23489734 | Q21: =DCF!Q125 -> 0.23197434 | R21: =DCF!R125 -> 0.231
B23: Taxes | D23: =D24*D17 -> 73.063064 | E23: =E24*E17 -> 88.145079 | F23: =F24*F17 -> 150.5146 | G23: =G24*G17 -> 147.40315 | H23: =H24*H17 -> 157.06464 | I23: =I24*I17 -> 86.46518 | J23: =J24*J17 -> 167.66032 | K23: =K24*K17 -> 279.58812 | ... R23: =R24*R17 -> 394.91229
B24: % tax rate | D24: =DCF!D61 -> 0.27801734 | E24: =DCF!E61 -> 0.28232745 | F24: =DCF!F61 -> 0.43768886 | G24: =DCF!G61 -> 0.32359175 | H24: =DCF!H61 -> 0.28058721 | I24: =DCF!I61 -> 0.28124367 | J24: =DCF!J61 -> 0.26880226 | K24: =DCF!K61 -> 0.35853324 | ... R24: =DCF!R61 -> 0.29833566
B26: EBIAT | D26: =D17-D23 -> 189.73732 | E26: =E17-E23 -> 224.0636 | F26: =F17-F23 -> 193.37032 | G26: =G17-G23 -> 308.11881 | H26: =H17-H23 -> 402.70656 | I26: =I17-I23 -> 220.97349 | J26: =J17-J23 -> 456.07074 | K26: =K17-K23 -> 500.22276 | ... R26: =R17-R23 -> 928.80574
B28: D&A | D28: =DCF!D65 -> 54.001984 | E28: =DCF!E65 -> 63.755121 | F28: =DCF!F65 -> 75.05517 | G28: =DCF!G65 -> 79.203218 | H28: =DCF!H65 -> 101.77812 | I28: =DCF!I65 -> 69.895652 | J28: =DCF!J65 -> 101.1084 | K28: =DCF!K65 -> 131.24817 | ... R28: =DCF!R65 -> 235.97661
B29: % of sales | E29: =DCF!E66 -> 0.72699318 | F29: =DCF!F66 -> 0.69344639 | G29: =DCF!G66 -> 0.64664134 | H29: =DCF!H66 -> 0.62851997 | I29: =DCF!I66 -> 0.37684066 | J29: =DCF!J66 -> 0.45096208 | K29: =DCF!K66 -> 0.44980197 | L29: =DCF!L66 -> 0.42586824 | ... R29: =DCF!R66 -> 0.42586824
B31: CapEx | D31: =DCF!D82 -> 105.59098 | E31: =DCF!E82 -> 108.69348 | F31: =DCF!F82 -> 109.47022 | G31: =DCF!G82 -> 146.01614 | H31: =DCF!H82 -> 177.90132 | I31: =DCF!I82 -> 86.381678 | J31: =DCF!J82 -> 177.90544 | K31: =DCF!K82 -> 287.26918 | ... R31: =DCF!R82 -> 335.1583
B32: % of sales | D32: =DCF!D83 -> 0.7358923 | E32: =DCF!E83 -> 0.72699318 | F32: =DCF!F83 -> 0.69344639 | G32: =DCF!G83 -> 0.64664134 | H32: =DCF!H83 -> 0.62851997 | I32: =DCF!I83 -> 0.37684066 | J32: =DCF!J83 -> 0.45096208 | K32: =DCF!K83 -> 0.44980197 | ... R32: =DCF!R83 -> 0.42586824
B34: Change in NWC | D34: =DCF!D98 -> 43.964413 | E34: =DCF!E98 -> -0.43837689 | F34: =DCF!F98 -> -72.553909 | G34: =DCF!G98 -> -72.989641 | H34: =DCF!H98 -> 121.9775 | I34: =DCF!I98 -> 17.918397 | J34: =DCF!J98 -> -58.233184 | K34: =DCF!K98 -> 268.52818 | ... R34: =DCF!R98 -> 117.36027
B35: % of sales | D35: =DCF!D99 -> 0.028994095 | E35: =DCF!E99 -> -0.00025720955 | F35: =DCF!F99 -> -0.03949447 | G35: =DCF!G99 -> -0.034326049 | H35: =DCF!H99 -> 0.048770184 | I35: =DCF!I99 -> 0.010801978 | J35: =DCF!J99 -> -0.020639109 | K35: =DCF!K99 -> 0.073607136 | ... R35: =DCF!R99 -> 0.019265858
B37: Unlevered FCF | D37: =D26+D28-D31-D34 -> 94.183914 | E37: =E26+E28-E31-E34 -> 179.56362 | F37: =F26+F28-F31-F34 -> 231.50918 | G37: =G26+G28-G31-G34 -> 314.29553 | H37: =H26+H28-H31-H34 -> 204.60586 | I37: =I26+I28-I31-I34 -> 186.56907 | J37: =J26+J28-J31-J34 -> 437.50689 | K37: =K26+K28-K31-K34 -> 75.67357 | ... R37: =R26+R28-R31-R34 -> 712.26378
B38: PV FCF | N38: =(N37*N40)/(1+D5)^N41 -> 20.888847 | O38: =O37/(1+$D$5)^O41 -> 506.30688 | P38: =P37/(1+$D$5)^P41 -> 513.16279 | Q38: =Q37/(1+$D$5)^Q41 -> 507.95827 | R38: =R37/(1+$D$5)^R41 -> 535.95765
B40: Period | N40: =DCF!N144 -> 0.041666667
B41: Discount Period | N41: =DCF!N145 -> 0.020833333 | O41: =DCF!O145 -> 0.52083333 | P41: =DCF!P145 -> 1.5208333 | Q41: =DCF!Q145 -> 2.5208333 | R41: =DCF!R145 -> 3.5208333
B43: Terminal Value | R43: =(R37*(1+D6))/(D5-D6) -> 12347.646
B44: PV TV | R44: =R43/(1+WACC)^R41 -> 9291.242
B46: Enterprise Value | R46: =SUM(N38:R38)+R44 -> 11375.516

Sheet Direct to Consumer DCF
B2: Direct to Consumer DCF
A4: x | B4: Assumptions
B5: WACC | D5: =WACC -> 0.084126282
B6: TGR | D6: =TGR -> 0.025
A9: x | B9: DCF | D9: 2015 | E9: 2016 | F9: 2017 | G9: 2018 | H9: 2019 | I9: 2020 | J9: 2021 | K9: 2022 | L9: 2023 | M9: 2024 | N9: 2025 | O9: 2026 | P9: 2027 | Q9: 2028 | R9: 2029
A11: x | B11: Revenue | D11: =DCF!D27 -> 401.525 | E11: =DCF!E27 -> 453.287 | F11: =DCF!F27 -> 577.59 | G11: =DCF!G27 -> 858.856 | H11: =DCF!H27 -> 1137.822 | I11: =DCF!I27 -> 2284.068 | J11: =DCF!J27 -> 2777.944 | K11: =DCF!K27 -> 3699.791 | ... M11: =DCF!M27 -> 5008.3873 | N11: =M11*(1+N12) -> 5310.0194 | O11: =N11*(1+O12) -> 5676.7039 | P11: =O11*(1+P12) -> 6130.8402 | Q11: =P11*(1+Q12) -> 6605.0161 | R11: =Q11*(1+R12) -> 7001.317
B12: % growth | E12: =DCF!E28 -> 0.12891352 | F12: =DCF!F28 -> 0.27422582 | G12: =DCF!G28 -> 0.4869648 | H12: =DCF!H28 -> 0.32481114 | I12: =DCF!I28 -> 1.0074036 | J12: =DCF!J28 -> 0.21622649 | K12: =DCF!K28 -> 0.33184506 | L12: =DCF!L28 -> 0.22982719 | M12: =DCF!M28 -> 0.10071941 | N12: =OFFSET(N12,DCF!$D$11,0) -> 0.060225388 | O12: =OFFSET(O12,DCF!$D$11,0) -> 0.069055212 | P12: =OFFSET(P12,DCF!$D$11,0) -> 0.08 | Q12: =OFFSET(Q12,DCF!$D$11,0) -> 0.077342721 | R12: =OFFSET(R12,DCF!$D$11,0) -> 0.06
B13: Conservative | N13: =DCF!N117 -> 0.060225388 | O13: =DCF!O117 -> 0.05524417 | P13: =DCF!P117 -> 0.064 | Q13: =DCF!Q117 -> 0.061874177 | R13: =DCF!R117 -> 0.048
B14: Base | N14: =DCF!N118 -> 0.060225388 | O14: =DCF!O118 -> 0.069055212 | P14: =DCF!P118 -> 0.08 | Q14: =DCF!Q118 -> 0.077342721 | R14: =DCF!R118 -> 0.06
B15: Optimisitic | N15: =DCF!N119 -> 0.060225388 | O15: =DCF!O119 -> 0.082866255 | P15: =DCF!P119 -> 0.096 | Q15: =DCF!Q119 -> 0.092811266 | R15: =DCF!R119 -> 0.072
B17: EBIT | D17: =DCF!D47 -> 69.590005 | E17: =DCF!E47 -> 83.034326 | F17: =DCF!F47 -> 108.12056 | G17: =DCF!G47 -> 183.98917 | H17: =DCF!H47 -> 254.65931 | I17: =DCF!I47 -> 423.3228 | J17: =DCF!J47 -> 614.10307 | K17: =DCF!K47 -> 790.8544 | ... M17: =DCF!M47 -> 1182.4426 | N17: =N11*N18 -> 1158.093 | O17: =O11*O18 -> 1222.277 | P17: =P11*P18 -> 1309.1982 | Q17: =Q11*Q18 -> 1392.9038 | R17: =R11*R18 -> 1470.2766
B18: % of sales | D18: =DCF!D48 -> 0.17331425 | E18: =DCF!E48 -> 0.18318268 | F18: =DCF!F48 -> 0.18719257 | G18: =DCF!G48 -> 0.21422587 | H18: =DCF!H48 -> 0.22381296 | I18: =DCF!I48 -> 0.18533722 | J18: =DCF!J48 -> 0.22106388 | K18: =DCF!K48 -> 0.21375651 | ... M18: =DCF!M48 -> 0.23609249 | N18: =OFFSET(N18,DCF!$D$11,0) -> 0.21809581 | O18: =OFFSET(O18,DCF!$D$11,0) -> 0.21531456 | P18: =OFFSET(P18,DCF!$D$11,0) -> 0.21354304 | Q18: =OFFSET(Q18,DCF!$D$11,0) -> 0.21088576 | R18: =OFFSET(R18,DCF!$D$11,0) -> 0.21
B19: Conservative | N19: =DCF!N123 -> 0.21809581 | O19: =DCF!O123 -> 0.19628623 | P19: =DCF!P123 -> 0.17665761 | Q19: =DCF!Q123 -> 0.15899185 | R19: =DCF!R123 -> 0.14309266
B20: Base | N20: =DCF!N124 -> 0.21809581 | O20: =DCF!O124 -> 0.21531456 | P20: =DCF!P124 -> 0.21354304 | Q20: =DCF!Q124 -> 0.21088576 | R20: =DCF!R124 -> 0.21
B21: Optimisitic | N21: =DCF!N125 -> 0.21809581 | O21: =DCF!O125 -> 0.23684601 | P21: =DCF!P125 -> 0.23489734 | Q21: =DCF!Q125 -> 0.23197434 | R21: =DCF!R125 -> 0.231
B23: Taxes | D23: =D17*D24 -> 19.347228 | E23: =E17*E24 -> 23.442869 | F23: =F17*F24 -> 47.323163 | G23: =G17*G24 -> 59.537379 | H23: =H17*H24 -> 71.454144 | I23: =I17*I24 -> 119.05686 | J23: =J17*J24 -> 165.07229 | K23: =K17*K24 -> 283.54759 | ... R23: =R17*R24 -> 438.63593
B24: % tax rate | D24: =DCF!D61 -> 0.27801734 | E24: =DCF!E61 -> 0.28232745 | F24: =DCF!F61 -> 0.43768886 | G24: =DCF!G61 -> 0.32359175 | H24: =DCF!H61 -> 0.28058721 | I24: =DCF!I61 -> 0.28124367 | J24: =DCF!J61 -> 0.26880226 | K24: =DCF!K61 -> 0.35853324 | ... R24: =DCF!R61 -> 0.29833566
B26: EBIAT | D26: =D17-D23 -> 50.242777 | E26: =E17-E23 -> 59.591456 | F26: =F17-F23 -> 60.797393 | G26: =G17-G23 -> 124.4518 | H26: =H17-H23 -> 183.20516 | I26: =I17-I23 -> 304.26595 | J26: =J17-J23 -> 449.03077 | K26: =K17-K23 -> 507.30681 | ... R26: =R17-R23 -> 1031.6406
B28: D&A | D28: =DCF!D69 -> 14.299821 | E28: =DCF!E69 -> 16.95617 | F28: =DCF!F69 -> 23.59803 | G28: =DCF!G69 -> 31.99085 | H28: =DCF!H69 -> 46.302394 | I28: =DCF!I69 -> 96.241711 | J28: =DCF!J69 -> 99.547681 | K28: =DCF!K69 -> 133.10688 | ... R28: =DCF!R69 -> 262.10332
B29: % of sales | D29: =DCF!D70 -> 0 | E29: =DCF!E70 -> 0.18576106 | F29: =DCF!F70 -> 0.39170756 | G29: =DCF!G70 -> 0.35565761 | H29: =DCF!H70 -> 0.44736368 | I29: =DCF!I70 -> 1.0785472 | J29: =DCF!J70 -> 0.034350702 | K29: =DCF!K70 -> 0.3371168 | ... R29: =DCF!R70 -> 0.37285389
B31: CapEx | D31: =DCF!D86 -> 27.960677 | E31: =DCF!E86 -> 28.907876 | F31: =DCF!F86 -> 34.418436 | G31: =DCF!G86 -> 58.977154 | H31: =DCF!H86 -> 80.933472 | I31: =DCF!I86 -> 118.94188 | J31: =DCF!J86 -> 175.15927 | K31: =DCF!K86 -> 291.33742 | ... R31: =DCF!R86 -> 372.26614
B32: % of sales | D32: =DCF!D87 -> 0.19486558 | E32: =DCF!E87 -> 0.19334949 | F32: =DCF!F87 -> 0.21802587 | G32: =DCF!G87 -> 0.26118391 | H32: =DCF!H87 -> 0.2859355 | I32: =DCF!I87 -> 0.51888478 | J32: =DCF!J87 -> 0.44400097 | K32: =DCF!K87 -> 0.45617197 | ... R32: =DCF!R87 -> 0.47301924
B34: Change in NWC | D34: =DCF!D102 -> 11.641854 | E34: =DCF!E102 -> -0.11658974 | F34: =DCF!F102 -> -22.811611 | G34: =DCF!G102 -> -29.481133 | H34: =DCF!H102 -> 55.491789 | I34: =DCF!I102 -> 24.672452 | J34: =DCF!J102 -> -57.334289 | K34: =DCF!K102 -> 272.33102 | ... R34: =DCF!R102 -> 130.35409
B35: % of sales | D35: =DCF!D103 -> 0.028994095 | E35: =DCF!E103 -> -0.00025720955 | F35: =DCF!F103 -> -0.03949447 | G35: =DCF!G103 -> -0.034326049 | H35: =DCF!H103 -> 0.048770184 | I35: =DCF!I103 -> 0.010801978 | J35: =DCF!J103 -> -0.020639109 | K35: =DCF!K103 -> 0.073607136 | ... R35: =DCF!R103 -> 0.019265858
B37: Unlevered FCF | D37: =D26+D28-D31-D34 -> 24.940066 | E37: =E26+E28-E31-E34 -> 47.756341 | F37: =F26+F28-F31-F34 -> 72.788598 | G37: =G26+G28-G31-G34 -> 126.94662 | H37: =H26+H28-H31-H34 -> 93.082293 | I37: =I26+I28-I31-I34 -> 256.89332 | J37: =J26+J28-J31-J34 -> 430.75347 | K37: =K26+K28-K31-K34 -> 76.745243 | ... R37: =R26+R28-R31-R34 -> 791.12373
B38: PV FCF | N38: =(N37*N40)/(1+D5)^N41 -> 23.201604 | O38: =O37/(1+$D$5)^O41 -> 562.36383 | P38: =P37/(1+$D$5)^P41 -> 569.97881 | Q38: =Q37/(1+$D$5)^Q41 -> 564.19807 | R38: =R37/(1+$D$5)^R41 -> 595.29746
B40: Period | N40: =DCF!N144 -> 0.041666667
B41: Discount Period | N41: =DCF!N145 -> 0.020833333 | O41: =DCF!O145 -> 0.52083333 | P41: =DCF!P145 -> 1.5208333 | Q41: =DCF!Q145 -> 2.5208333 | R41: =DCF!R145 -> 3.5208333
B43: Terminal Value | R43: =(R37*(1+D6))/(D5-D6) -> 13714.744
B44: PV TV | R44: =R43/(1+WACC)^R41 -> 10319.944
B46: Enterprise Value | R46: =SUM(N38:R38)+R44 -> 12634.983

Sheet Other DCF
B2: Other DCF
A4: x | B4: Assumptions
B5: WACC | D5: =WACC -> 0.084126282
B6: TGR | D6: =TGR -> 0.025
A9: x | B9: DCF | D9: 2015 | E9: 2016 | F9: 2017 | G9: 2018 | H9: 2019 | I9: 2020 | J9: 2021 | K9: 2022 | L9: 2023 | M9: 2024 | N9: 2025 | O9: 2026 | P9: 2027 | Q9: 2028 | R9: 2029
A11: x | B11: Revenue | D11: =DCF!D31 -> 142.675 | E11: =DCF!E31 -> 186.748 | F11: =DCF!F31 -> 234.526 | G11: =DCF!G31 -> 303.1 | H11: =DCF!H31 -> 340.407 | I11: =DCF!I31 -> 459.004 | J11: =DCF!J31 -> 657.176 | K11: =DCF!K31 -> 762.6 | ... M11: =DCF!M31 -> 1070.5921 | N11: =M11*(1+N12) -> 1135.069 | O11: =N11*(1+O12) -> 1213.4514 | P11: =O11*(1+P12) -> 1310.5275 | Q11: =P11*(1+Q12) -> 1411.8873 | R11: =Q11*(1+R12) -> 1496.6005
B12: % growth | E12: =DCF!E28 -> 0.12891352 | F12: =DCF!F28 -> 0.27422582 | G12: =DCF!G28 -> 0.4869648 | H12: =DCF!H28 -> 0.32481114 | I12: =DCF!I28 -> 1.0074036 | J12: =DCF!J28 -> 0.21622649 | K12: =DCF!K28 -> 0.33184506 | L12: =DCF!L28 -> 0.22982719 | M12: =DCF!M28 -> 0.10071941 | N12: =OFFSET(N12,DCF!$D$11,0) -> 0.060225388 | O12: =OFFSET(O12,DCF!$D$11,0) -> 0.069055212 | P12: =OFFSET(P12,DCF!$D$11,0) -> 0.08 | Q12: =OFFSET(Q12,DCF!$D$11,0) -> 0.077342721 | R12: =OFFSET(R12,DCF!$D$11,0) -> 0.06
B13: Conservative | N13: =DCF!N117 -> 0.060225388 | O13: =DCF!O117 -> 0.05524417 | P13: =DCF!P117 -> 0.064 | Q13: =DCF!Q117 -> 0.061874177 | R13: =DCF!R117 -> 0.048
B14: Base | N14: =DCF!N118 -> 0.060225388 | O14: =DCF!O118 -> 0.069055212 | P14: =DCF!P118 -> 0.08 | Q14: =DCF!Q118 -> 0.077342721 | R14: =DCF!R118 -> 0.06
B15: Optimisitic | N15: =DCF!N119 -> 0.060225388 | O15: =DCF!O119 -> 0.082866255 | P15: =DCF!P119 -> 0.096 | Q15: =DCF!Q119 -> 0.092811266 | R15: =DCF!R119 -> 0.072
B17: EBIT | D17: =DCF!D51 -> 24.727611 | E17: =DCF!E51 -> 34.208998 | F17: =DCF!F51 -> 43.901525 | G17: =DCF!G51 -> 64.931861 | H17: =DCF!H51 -> 76.187497 | I17: =DCF!I51 -> 85.070524 | J17: =DCF!J51 -> 145.27787 | K17: =DCF!K51 -> 163.01071 | ... M17: =DCF!M51 -> 252.75876 | N17: =N11*N18 -> 247.55379 | O17: =O11*O18 -> 261.27375 | P17: =P11*P18 -> 279.85402 | Q17: =Q11*Q18 -> 297.74692 | R17: =R11*R18 -> 314.28611
B18: % of sales | D18: =DCF!D48 -> 0.17331425 | E18: =DCF!E48 -> 0.18318268 | F18: =DCF!F48 -> 0.18719257 | G18: =DCF!G48 -> 0.21422587 | H18: =DCF!H48 -> 0.22381296 | I18: =DCF!I48 -> 0.18533722 | J18: =DCF!J48 -> 0.22106388 | K18: =DCF!K48 -> 0.21375651 | ... M18: =DCF!M48 -> 0.23609249 | N18: =OFFSET(N18,DCF!$D$11,0) -> 0.21809581 | O18: =OFFSET(O18,DCF!$D$11,0) -> 0.21531456 | P18: =OFFSET(P18,DCF!$D$11,0) -> 0.21354304 | Q18: =OFFSET(Q18,DCF!$D$11,0) -> 0.21088576 | R18: =OFFSET(R18,DCF!$D$11,0) -> 0.21
B19: Conservative | N19: =DCF!N123 -> 0.21809581 | O19: =DCF!O123 -> 0.19628623 | P19: =DCF!P123 -> 0.17665761 | Q19: =DCF!Q123 -> 0.15899185 | R19: =DCF!R123 -> 0.14309266
B20: Base | N20: =DCF!N124 -> 0.21809581 | O20: =DCF!O124 -> 0.21531456 | P20: =DCF!P124 -> 0.21354304 | Q20: =DCF!Q124 -> 0.21088576 | R20: =DCF!R124 -> 0.21
B21: Optimisitic | N21: =DCF!N125 -> 0.21809581 | O21: =DCF!O125 -> 0.23684601 | P21: =DCF!P125 -> 0.23489734 | Q21: =DCF!Q125 -> 0.23197434 | R21: =DCF!R125 -> 0.231
B23: Taxes | D23: =D17*D24 -> 6.8747046 | E23: =E17*E24 -> 9.6581392 | F23: =F17*F24 -> 19.215208 | G23: =G17*G24 -> 21.011415 | H23: =H17*H24 -> 21.377237 | I23: =I17*I24 -> 23.925546 | J23: =J17*J24 -> 39.05102 | K23: =K17*K24 -> 58.444759 | ... R23: =R17*R24 -> 93.762752
B24: % tax rate | D24: =DCF!D61 -> 0.27801734 | E24: =DCF!E61 -> 0.28232745 | F24: =DCF!F61 -> 0.43768886 | G24: =DCF!G61 -> 0.32359175 | H24: =DCF!H61 -> 0.28058721 | I24: =DCF!I61 -> 0.28124367 | J24: =DCF!J61 -> 0.26880226 | K24: =DCF!K61 -> 0.35853324 | ... R24: =DCF!R61 -> 0.29833566
B26: EBIAT | D26: =D17-D23 -> 17.852906 | E26: =E17-E23 -> 24.550859 | F26: =F17-F23 -> 24.686316 | G26: =G17-G23 -> 43.920447 | H26: =H17-H23 -> 54.81026 | I26: =I17-I23 -> 61.144977 | J26: =J17-J23 -> 106.22685 | K26: =K17-K23 -> 104.56595 | ... R26: =R17-R23 -> 220.52335
B28: D&A | D28: =DCF!D73 -> 5.0811952 | E28: =DCF!E73 -> 6.9857086 | F28: =DCF!F73 -> 9.5817997 | G28: =DCF!G73 -> 11.289933 | H28: =DCF!H73 -> 13.852482 | I28: =DCF!I73 -> 19.340637 | J28: =DCF!J73 -> 23.549916 | K28: =DCF!K73 -> 27.435956 | ... R28: =DCF!R73 -> 56.027167
B29: % of sales | D29: =DCF!D70 -> 0 | E29: =DCF!E70 -> 0.18576106 | F29: =DCF!F70 -> 0.39170756 | G29: =DCF!G70 -> 0.35565761 | H29: =DCF!H70 -> 0.44736368 | I29: =DCF!I70 -> 1.0785472 | J29: =DCF!J70 -> 0.034350702 | K29: =DCF!K70 -> 0.3371168 | ... R29: =DCF!R70 -> 0.37285389
B31: CapEx | D31: =DCF!D90 -> 9.9353454 | E31: =DCF!E90 -> 11.909647 | F31: =DCF!F90 -> 13.975343 | G31: =DCF!G90 -> 20.813705 | H31: =DCF!H90 -> 24.213208 | I31: =DCF!I90 -> 23.902441 | J31: =DCF!J90 -> 41.437289 | K31: =DCF!K90 -> 60.050397 | ... R31: =DCF!R90 -> 79.575556
B32: % of sales | D32: =DCF!D87 -> 0.19486558 | E32: =DCF!E87 -> 0.19334949 | F32: =DCF!F87 -> 0.21802587 | G32: =DCF!G87 -> 0.26118391 | H32: =DCF!H87 -> 0.2859355 | I32: =DCF!I87 -> 0.51888478 | J32: =DCF!J87 -> 0.44400097 | K32: =DCF!K87 -> 0.45617197 | ... R32: =DCF!R87 -> 0.47301924
B34: Change in NWC | D34: =DCF!D106 -> 4.1367325 | E34: =DCF!E106 -> -0.048033368 | F34: =DCF!F106 -> -9.2624801 | G34: =DCF!G106 -> -10.404226 | H34: =DCF!H106 -> 16.601712 | I34: =DCF!I106 -> 4.9581511 | J34: =DCF!J106 -> -13.563527 | K34: =DCF!K106 -> 56.132802 | ... R34: =DCF!R106 -> 27.864472
B35: % of sales | D35: =DCF!D103 -> 0.028994095 | E35: =DCF!E103 -> -0.00025720955 | F35: =DCF!F103 -> -0.03949447 | G35: =DCF!G103 -> -0.034326049 | H35: =DCF!H103 -> 0.048770184 | I35: =DCF!I103 -> 0.010801978 | J35: =DCF!J103 -> -0.020639109 | K35: =DCF!K103 -> 0.073607136 | ... R35: =DCF!R103 -> 0.019265858
B37: Unlevered FCF | D37: =D26+D28-D31-D34 -> 8.8620234 | E37: =E26+E28-E31-E34 -> 19.674955 | F37: =F26+F28-F31-F34 -> 29.555253 | G37: =G26+G28-G31-G34 -> 44.8009 | H37: =H26+H28-H31-H34 -> 27.847822 | I37: =I26+I28-I31-I34 -> 51.625023 | J37: =J26+J28-J31-J34 -> 101.90301 | K37: =K26+K28-K31-K34 -> 15.81871 | ... R37: =R26+R28-R31-R34 -> 169.11049
B38: PV FCF | N38: =(N37*N40)/(1+D5)^N41 -> 4.9595715 | O38: =O37/(1+$D$5)^O41 -> 120.21081 | P38: =P37/(1+$D$5)^P41 -> 121.83859 | Q38: =Q37/(1+$D$5)^Q41 -> 120.6029 | R38: =R37/(1+$D$5)^R41 -> 127.2507
B40: Period | N40: =DCF!N144 -> 0.041666667
B41: Discount Period | N41: =DCF!N145 -> 0.020833333 | O41: =DCF!O145 -> 0.52083333 | P41: =DCF!P145 -> 1.5208333 | Q41: =DCF!Q145 -> 2.5208333 | R41: =DCF!R145 -> 3.5208333
B43: Terminal Value | R43: =(R37*(1+D6))/(D5-D6) -> 2931.6617
B44: PV TV | R44: =R43/(1+WACC)^R41 -> 2205.9896
B46: Enterprise Value | R46: =SUM(N38:R38)+R44 -> 2700.8522

Sheet WACC
B1: in millions
B2: WACC
B3: (% of Equity * cost of equity) + (% of debt * cost of debt) * (1 - Tax) | H3: Beta
B4: Cost of Equity = Risk Free Rate + (Beta * Market Risk Premium) | H4: Use from source
B6: WACC | H6: Market Risk Premium
B7: Market Cap | F7: 27098.24 | H7: damodaran Online
B8: % of Equity | F8: =F7/(F7+F14) -> 0.94504437
B9: Cost of Equity | F9: =F10+(F11*F12) -> 0.086776 | H9: Risk Free Rate
B10: Risk Free Rate | F10: 0.04383 | H10: Use 10 Year Treasury
B11: Beta | F11: 1.09
B12: Market Risk Premium | F12: 0.0394
B14: Debt | F14: =275.2+1300.6 -> 1575.8
B15: % of Debt | F15: =F14/(F7+F14) -> 0.054955632
B16: Cost of Debt | F16: =(F14/F19) -> 0.054955632
B17: Tax Rate | F17: =DCF!L19 -> 0.29833566
B19: Total | F19: =F7+F14 -> 28674.04
B21: WACC | F21: =F8*F9+(F15*F16*(1-F17)) -> 0.084126282

Sheet Shares
B2: Diluted Share Count Calculation
A4: x | B4: Full Diluted Shares
B6: Current Stock Price | E6: =DCF!I4 -> 205.57
B7: Basic shares outstanding (latest filing) | E7: 115.52123
B8: In the money exercisable options | E8: =E30 -> 0
B9: Total proceeds ($mm) | E9: =SUMPRODUCT(D19:D28,E19:E28) -> 0
B10: Total shares repurchased (mm) | E10: =E9/E6 -> 0
B11: Net dilutive options | E11: =E8-E10 -> 0
B12: Dilutive impact of shares from other securities | E12: 0.849
B14: Net diluted shares outstanding | E14: =E7+E11+E12 -> 116.37023
A16: x | B16: Options outstanding
C18: Outstanding | D18: Exercise Price | E18: Diliutive Shares
B19: Tranche 1 | E19: =IF(D19<$E$6,C19) -> 0
B20: Tranche 2 | E20: =IF(D20<$E$6,C20) -> 0
B21: Tranche 3 | E21: =IF(D21<$E$6,C21) -> 0
B22: Tranche 4 | E22: =IF(D22<$E$6,C22) -> 0
B23: Tranche 5 | E23: =IF(D23<$E$6,C23) -> 0
B24: Tranche 6 | E24: =IF(D24<$E$6,C24) -> 0
B25: Tranche 7 | E25: =IF(D25<$E$6,C25) -> 0
B26: Tranche 8 | E26: =IF(D26<$E$6,C26) -> 0
B27: Tranche 9 | E27: =IF(D27<$E$6,C27) -> 0
B28: Tranche 10 | E28: =IF(D28<$E$6,C28) -> 0
B30: Total | E30: =SUM(E19:E28) -> 0

Sheet IS
A1: lululemon athletica inc. (LULU)
A2: $226.11
A5: lululemon athletica inc.
A6: LULU 550021109 B23FN39 NASDAQ Common stock
A7: Source: FactSet Fundamentals
B8: JAN '16 | C8: JAN '17 | D8: JAN '18 | E8: JAN '19 | F8: JAN '20 | G8: JAN '21 | H8: JAN '22 | I8: JAN '23 | J8: JAN '24 | K8: JAN '25 | L8: APR '25
L9: LTM
A10: Sales | B10: 2060.523 | C10: 2344.392 | D10: 2649.181 | E10: 3288.319 | F10: 3979.296 | G10: 4401.879 | H10: 6256.617 | I10: 8110.518 | J10: 9619.278 | K10: 10588.126 | L10: 10749.895
A11: Cost of Goods Sold (COGS) incl. D&A | B11: 1063.357 | C11: 1144.775 | D11: 1241.693 | E11: 1472.032 | F11: 1755.91 | G11: 1943.048 | H11: 2656.834 | I11: 3626.93 | J11: 4014.883 | K11: 4320.05 | L11: 4375.391
A12: COGS excluding D&A | B12: 989.974 | C12: 1057.078 | D12: 1133.458 | E12: 1349.548 | F12: 1594.11 | G12: 1757.788 | H12: 2432.628 | I12: 3335.139 | J12: 3635.499 | K12: 3873.526 | L12: 3910.097
A13: Depreciation & Amortization Expense | B13: 73.383 | C13: 87.697 | D13: 108.235 | E13: 122.484 | F13: 161.8 | G13: 185.26 | H13: 224.206 | I13: 291.791 | J13: 379.384 | K13: 446.524 | L13: 465.294
A14: Depreciation | B14: 72.573 | C14: 86.997 | D14: 108.235 | E14: 122.484 | F14: 161.8 | G14: 180.1 | H14: 215.424 | I14: 283.039 | J14: 374.374 | K14: 443.789 | L14: 460.929
A15: Amortization of Intangibles | B15: 0.81 | C15: 0.7 | D15: 0 | G15: 5.16 | H15: 8.782 | I15: 8.752 | J15: 5.01 | K15: 2.735 | L15: 4.365
A16: Gross Income | B16: 997.166 | C16: 1199.617 | D16: 1407.488 | E16: 1816.287 | F16: 2223.386 | G16: 2458.831 | H16: 3599.783 | I16: 4483.588 | J16: 5604.395 | K16: 6268.076 | L16: 6374.504
A17: SG&A Expense | B17: 640.048 | C17: 770.165 | D17: 911.581 | E17: 1111.844 | F17: 1332.768 | G17: 1642.999 | H17: 2216.671 | I17: 2749.912 | J17: 3396.751 | K17: 3768.299 | L17: 3826.255
A18: Other SG&A | B18: 640.048 | C18: 770.165 | D18: 911.581 | E18: 1111.844 | F18: 1332.768 | G18: 1642.999 | H18: 2216.671 | I18: 2749.912 | J18: 3396.751 | K18: 3768.299 | L18: 3826.255
A19: EBIT (Operating Income) | B19: 357.118 | C19: 429.452 | D19: 495.907 | E19: 704.443 | F19: 890.618 | G19: 815.832 | H19: 1383.112 | I19: 1733.676 | J19: 2207.644 | K19: 2499.777 | L19: 2548.249
A20: Nonoperating Income - Net | B20: 11.377 | C20: -6.723 | D20: 3.997 | E20: 33.056 | F20: 10.984 | G20: -26.689 | H20: 12.025 | I20: 18.753 | J20: 19.827 | K20: 198.223 | L20: 66.842
A21: Other Income (Expense) | B21: 11.377 | C21: -6.723 | D21: 3.997 | E21: 33.056 | F21: 10.984 | G21: -26.689 | H21: 12.025 | I21: 18.753 | J21: 19.827 | K21: 198.223 | L21: 66.842
A22: Unusual Expense - Net | D22: 39.906 | E22: 22.249 | F22: 4.209 | G22: -30.207 | H22: 61.268 | I22: 419.858 | J22: 51.736 | K22: 121.923 | L22: 44.528
A23: Impairments | I23: 407.913 | J23: 44.186
A24: Goodwill | B24: 0 | C24: 0 | D24: 0 | E24: 0 | F24: 0 | G24: 0 | H24: 0 | I24: 362.492 | J24: 0 | K24: 0 | L24: 0
A25: Other Intangibles | B25: 0 | C25: 0 | D25: 0 | E25: 0 | F25: 0 | G25: 0 | H25: 0 | I25: 40.585 | J25: 33.025 | K25: 0 | L25: 0
A26: Property,Plant & Equipment | I26: 4.836 | J26: 11.161
A27: Restructuring Expense | B27: 0 | C27: 0 | D27: 47.223 | E27: 0 | F27: 0 | G27: 29.842 | H27: 41.394 | I27: 0 | J27: 30.315 | K27: 3.5 | L27: 3.5
A28: Unrealized Valuation Gain/Loss | D28: 7.317 | E28: -22.249 | F28: -4.209 | G28: 22.949 | H28: -19.874 | I28: -11.945 | J28: 22.765 | K28: -118.423 | L28: -41.028
A29: Hedges/Derivatives | D29: 7.317 | E29: -22.249 | F29: -4.209 | G29: 22.949 | H29: -19.874 | I29: -11.945 | J29: 22.765 | K29: -118.423 | L29: -41.028
A30: Excpl Chrgs - Others | G30: -37.1
A31: Other Unusual Expense | G31: -37.1
A32: Pretax Income | B32: 368.495 | C32: 422.729 | D32: 459.998 | E32: 715.25 | F32: 897.393 | G32: 819.35 | H32: 1333.869 | I32: 1332.571 | J32: 2175.735 | K32: 2576.077 | L32: 2570.563
A33: Income Taxes | B33: 102.448 | C33: 119.348 | D33: 201.336 | E33: 231.449 | F33: 251.797 | G33: 230.437 | H33: 358.547 | I33: 477.771 | J33: 625.545 | K33: 761.461 | L33: 762.796
A34: Income Taxes - Current Domestic | B34: -15.299 | C34: 42.935 | D34: 91.297 | E34: 89.366 | F34: 57.245 | G34: 10.509 | H34: 43.309 | I34: 68.121 | J34: 183.202 | K34: 118.834
A35: Income Taxes - Current Foreign | B35: 110.372 | C35: 94.581 | D35: 109.322 | E35: 123.129 | F35: 170.158 | G35: 185.803 | H35: 322.105 | I35: 400.25 | J35: 469.09 | K35: 584.248
A36: Income Taxes - Deferred Domestic | B36: 9.144 | C36: -12.905 | D36: 18.431 | E36: -21.634 | F36: -5.833 | G36: 25.677 | H36: 6.903 | I36: 11.295 | J36: -17.838 | K36: 75.433
A37: Income Taxes - Deferred Foreign | B37: -1.769 | C37: -5.263 | D37: -17.714 | E37: 40.588 | F37: 30.227 | G37: 8.448 | H37: -13.77 | I37: -1.895 | J37: -8.909 | K37: -17.054
A38: Consolidated Net Income | B38: 266.047 | C38: 303.381 | D38: 258.662 | E38: 483.801 | F38: 645.596 | G38: 588.913 | H38: 975.322 | I38: 854.8 | J38: 1550.19 | K38: 1814.616 | L38: 1807.767
A39: Net Income | B39: 266.047 | C39: 303.381 | D39: 258.662 | E39: 483.801 | F39: 645.596 | G39: 588.913 | H39: 975.322 | I39: 854.8 | J39: 1550.19 | K39: 1814.616 | L39: 1807.767
A40: Net Income available to Common | B40: 266.047 | C40: 303.381 | D40: 258.662 | E40: 483.801 | F40: 645.596 | G40: 588.913 | H40: 975.322 | I40: 854.8 | J40: 1550.19 | K40: 1814.616 | L40: 1807.767
A41: Per Share
A42: EPS (recurring) | B42: 1.892092 | C42: 2.209589 | D42: 2.104261 | E42: 3.727488 | F42: 4.952406 | G42: 4.33838 | H42: 7.814648 | I42: 8.973032 | J42: 12.485481 | K42: 15.330311 | L42: 15.217568
A43: EPS (basic) | B43: 1.9 | C43: 2.21 | D43: 1.9 | E43: 3.6263 | F43: 4.9512 | G43: 4.52 | H43: 7.5159 | I43: 6.6956 | J43: 12.2326 | K43: 14.6653 | L43: 14.6743
A44: Basic Shares Outstanding | B44: 140.365 | C44: 137.086 | D44: 135.988 | E44: 133.413 | F44: 130.393 | G44: 130.289 | H44: 129.768 | I44: 127.666 | J44: 126.726 | K44: 123.735 | L44: 120.632
A45: Total Shares Outstanding | B45: 137.286 | C45: 137.085 | D45: 135.431 | E45: 130.932 | F45: 130.349 | G45: 130.353 | H45: 128.5 | I45: 127.321 | J45: 126.222 | K45: 121.282 | L45: 120.025
A46: EPS (diluted) | B46: 1.89 | C46: 2.21 | D46: 1.9 | E46: 3.6112 | F46: 4.9299 | G46: 4.5 | H46: 7.4855 | I46: 6.6772 | J46: 12.2005 | K46: 14.6417 | L46: 14.6541
A47: Diluted Shares Outstanding | B47: 140.61 | C47: 137.302 | D47: 136.198 | E47: 133.971 | F47: 130.955 | G47: 130.871 | H47: 130.295 | I47: 128.017 | J47: 127.06 | K47: 123.935 | L47: 120.843
A48: Total Shares Outstanding | B48: 137.286 | C48: 137.085 | D48: 135.431 | E48: 130.932 | F48: 130.349 | G48: 130.353 | H48: 128.5 | I48: 127.321 | J48: 126.222 | K48: 121.282 | L48: 120.025
A49: Earnings Persistence | B49: 76.45 | C49: 80.936 | D49: 87.596 | E49: 88.884 | F49: 61.494 | G49: 73.299 | H49: 90.401 | I49: 76.906 | J49: 87.275 | K49: 82.828
A50: EBITDA
A51: EBITDA | B51: 430.501 | C51: 517.149 | D51: 604.142 | E51: 826.927 | F51: 1052.418 | G51: 1001.092 | H51: 1607.318 | I51: 2025.467 | J51: 2587.028 | K51: 2946.301 | L51: 3013.543
A52: EBIT | B52: 357.118 | C52: 429.452 | D52: 495.907 | E52: 704.443 | F52: 890.618 | G52: 815.832 | H52: 1383.112 | I52: 1733.676 | J52: 2207.644 | K52: 2499.777 | L52: 2548.249
A53: Depreciation & Amortization Expense | B53: 73.383 | C53: 87.697 | D53: 108.235 | E53: 122.484 | F53: 161.8 | G53: 185.26 | H53: 224.206 | I53: 291.791 | J53: 379.384 | K53: 446.524 | L53: 465.294
A54: All figures in millions of U.S. Dollar except per share items.
A56: Estimates
A57: LULU-US
A58: Income Statement (M)
B59: Jan '21 | C59: Jan '22 | D59: Jan '23 | E59: Jan '24 | F59: Jan '25 | G59: Jan '26E | H59: Jan '27E | I59: Jan '28E | J59: Jan '29E | K59: Jan '30E
A60: Sales | B60: 4401.88 | C60: 6256.62 | D60: 8110.52 | E60: 9619.28 | F60: 10588.1 | G60: 11225.8 | H60: 12001 | I60: 12732.5 | J60: 13158.7 | K60: 14304
A61: Guidance (Low) | B61: - | C61: 6250 | D61: 7944 | E61: 9549 | F61: 10452 | G61: 11150 | H61: - | I61: - | J61: - | K61: -
A62: Guidance (High) | B62: - | C62: 6290 | D62: 7994 | E62: 9584 | F62: 10487 | G62: 11300 | H62: - | I62: - | J62: - | K62: -
A63: Cost of Sales | B63: 1937.9 | C63: 2648.1 | D63: 3555.3 | E63: 3986.2 | F63: 4317.3 | G63: 4705.47 | H63: 5033.33 | I63: 5410 | J63: 5712 | K63: 6029
A64: Gross Income | B64: 2464 | C64: 3608.6 | D64: 4555.27 | E64: 5633.1 | F64: 6270.8 | G64: 6505.59 | H64: 6925.68 | I64: 7131.5 | J64: 7841 | K64: 8275
A65: EBITDA | B65: 1033.3 | C65: 1599 | D65: 2080.9 | E65: 2610 | F65: 2952.2 | G65: 2970.57 | H65: 3113.45 | I65: 3284.02 | J65: 3469.76 | K65: 3763
A66: Operating Income | B66: 848 | C66: 1374.75 | D66: 1789.08 | E66: 2230.9 | F66: 2505.7 | G66: 2448.3 | H66: 2583.99 | I66: 2656.59 | J66: 2808.19 | K66: 3158
A67: Pretax Income | B67: 847.1 | C67: 1375.21 | D67: 1793.2 | E67: 2273.95 | F67: 2576.1 | G67: 2498.63 | H67: 2633.56 | I67: 2705.6 | J67: 2847.73 | K67: 3176
A68: Tax Expense | B68: 233.6 | C68: 360 | D68: 504 | E68: 651.6 | F68: 761.5 | G68: 743.411 | H68: 779.986 | I68: 669.5 | J68: 869 | K68: 921
A69: Net Income | B69: 615.622 | C69: 1015.3 | D69: 1288.95 | E69: 1622.31 | F69: 1814.62 | G69: 1747.72 | H69: 1841.7 | I69: 1896.35 | J69: 2006.32 | K69: 2255

Sheet BS
A1: lululemon athletica inc. (LULU)
A2: $226.11
A5: lululemon athletica inc.
A6: LULU 550021109 B23FN39 NASDAQ Common stock
A7: Source: FactSet Fundamentals
B8: JAN '16 | C8: JAN '17 | D8: JAN '18 | E8: JAN '19 | F8: JAN '20 | G8: JAN '21 | H8: JAN '22 | I8: JAN '23 | J8: JAN '24 | K8: JAN '25
A9: Assets
A10: Cash & Short-Term Investments | B10: 501.482 | C10: 734.846 | D10: 990.501 | E10: 881.32 | F10: 1093.505 | G10: 1150.517 | H10: 1259.871 | I10: 1154.867 | J10: 2243.971 | K10: 1984.336
A11: Cash Only | B11: 501.482 | C11: 734.846 | D11: 990.501 | E11: 817.798 | F11: 890.145 | G11: 967.502 | H11: 941.173 | I11: 1154.859 | J11: 2243.963 | K11: 1984.328
A12: Total Short Term Investments | B12: 0 | C12: 0 | D12: 0 | E12: 63.522 | F12: 203.36 | G12: 183.015 | H12: 318.698 | I12: 0.008 | J12: 0.008 | K12: 0.008
A13: Short-Term Receivables | B13: 13.108 | C13: 9.2 | D13: 19.173 | E13: 35.786 | F13: 40.219 | G13: 75.708 | H13: 77.001 | I13: 132.906 | J13: 124.769 | K13: 120.173
A14: Accounts Receivables, Net | B14: 13.108 | C14: 9.2 | D14: 19.173 | E14: 35.786 | F14: 40.219 | G14: 62.399 | H14: 77.001 | I14: 132.906 | J14: 124.769 | K14: 120.173
A15: Accounts Receivables, Gross | B15: 13.108 | C15: 9.2 | D15: 19.173 | E15: 35.786 | F15: 40.219 | G15: 62.399 | H15: 77.001 | I15: 132.906 | J15: 124.769 | K15: 120.173
A16: Other Receivables | B16: 0 | C16: 0 | D16: 0 | E16: 0 | F16: 0 | G16: 13.309 | H16: 0 | I16: 0 | J16: 0 | K16: 0
A17: Inventories | B17: 284.009 | C17: 298.432 | D17: 329.562 | E17: 404.842 | F17: 518.513 | G17: 647.23 | H17: 966.481 | I17: 1447.367 | J17: 1323.602 | K17: 1442.081
A18: Finished Goods | B18: 290.791 | C18: 306.087 | D18: 344.695 | E18: 420.931 | F18: 540.58 | G18: 678.2 | H18: 1004.526 | I18: 1571.981 | J18: 1465.076 | K18: 1526.055
A19: Progress Payments & Other | B19: -6.782 | C19: -7.655 | D19: -15.133 | E19: -16.089 | F19: -22.067 | G19: -30.97 | H19: -38.045 | I19: -124.614 | J19: -141.474 | K19: -83.974
A20: Other Current Assets | B20: 118.44 | C20: 120.259 | D20: 97.046 | E20: 107.334 | F20: 155.701 | G20: 250.924 | H20: 311.5 | I20: 424.313 | J20: 368.235 | K20: 433.712
A21: Prepaid Expenses | G21: 82.164 | H21: 140.945 | I21: 142.003 | J21: 137.203 | K21: 147.68
A22: Miscellaneous Current Assets | B22: 118.44 | C22: 120.259 | D22: 97.046 | E22: 107.334 | F22: 155.701 | G22: 168.76 | H22: 170.555 | I22: 282.31 | J22: 231.032 | K22: 286.032
A23: Total Current Assets | B23: 917.039 | C23: 1162.737 | D23: 1436.282 | E23: 1429.282 | F23: 1807.938 | G23: 2124.379 | H23: 2614.853 | I23: 3159.453 | J23: 4060.577 | K23: 3980.302
A24: Net Property, Plant & Equipment | B24: 349.605 | C24: 423.499 | D24: 473.642 | E24: 567.237 | F24: 1361.357 | G24: 1480.522 | H24: 1731.253 | I24: 2239.033 | J24: 2811.421 | K24: 3196.873
A25: Property, Plant & Equipment - Gross | B25: 553.406 | C25: 701.824 | D25: 817.35 | E25: 972.481 | F25: 1883.033 | G25: 2171.109 | H25: 2560.387 | I25: 3226.331 | J25: 4028.846 | K25: 4657.922
A26: Buildings | B26: 30.885 | C26: 32.174 | D26: 39.278 | E26: 38.03 | F26: 30.187 | G26: 30.87 | H26: 30.88 | I26: 28.85 | J26: 29.032 | K26: 27.655
A27: Land & Improvements | B27: 55.488 | C27: 78.561 | D27: 83.048 | E27: 78.636 | F27: 71.829 | G27: 74.261 | H27: 74.297 | I27: 80.692 | J27: 79.498 | K27: 74.461
A28: Construction in Progress | D28: 51.26 | E28: 74.271 | F28: 40.93 | G28: 69.847 | H28: 163.42 | I28: 244.898 | J28: 247.943 | K28: 206.398
A29: Computer Software and Equipment | B29: 156.246 | C29: 219.105 | D29: 235.731 | E29: 300.231 | F29: 432.167 | G29: 543.552 | H29: 663.212 | I29: 909.063 | J29: 1209.164 | K29: 1476.801
A30: Transportation Equipment | B30: 11.929 | C30: 13.704 | D30: 14.806
A31: Other Property, Plant & Equipment | B31: 298.858 | C31: 358.28 | D31: 393.227 | E31: 481.313 | F31: 618.256 | G31: 717.744 | H31: 825.035 | I31: 993.409 | J31: 1197.599 | K31: 1456.351
A32: Operating Lease Right-of-Use Assets | F32: 689.664 | G32: 734.835 | H32: 803.543 | I32: 969.419 | J32: 1265.61 | K32: 1416.256
A33: Accumulated Depreciation | B33: 203.801 | C33: 278.325 | D33: 343.708 | E33: 405.244 | F33: 521.676 | G33: 690.587 | H33: 829.134 | I33: 987.298 | J33: 1217.425 | K33: 1461.049
A34: Intangible Assets | B34: 24.777 | C34: 24.557 | D34: 24.679 | E34: 24.239 | F34: 24.423 | G34: 466.957 | H34: 458.179 | I34: 46.105 | J34: 24.083 | K34: 171.191
A35: Goodwill | B35: 23.83 | C35: 24.233 | D35: 24.606 | E35: 24.239 | F35: 24.423 | G35: 386.877 | H35: 386.88 | I35: 24.144 | J35: 24.083 | K35: 159.518
A36: Other Intangible Assets | B36: 0.947 | C36: 0.324 | D36: 0.073 | E36: 0 | F36: 0 | G36: 80.08 | H36: 71.299 | I36: 21.961 | J36: 0 | K36: 11.673
A37: Deferred Tax Assets | B37: 11.802 | C37: 26.256 | D37: 32.491 | E37: 26.549 | F37: 31.435 | G37: 6.731 | H37: 6.091 | I37: 6.402 | J37: 9.176 | K37: 17.085
A38: Other Assets | B38: 10.854 | C38: 20.492 | D38: 31.389 | E38: 37.404 | F38: 56.201 | G38: 106.626 | H38: 132.102 | I38: 156.045 | J38: 186.684 | K38: 237.841
A39: Deferred Charges | F39: 0 | H39: 89.334 | I39: 114.7 | J39: 133.597 | K39: 161.759
A40: Tangible Other Assets | B40: 10.854 | C40: 20.492 | D40: 31.389 | E40: 37.404 | F40: 56.201 | G40: 106.626 | H40: 42.768 | I40: 41.345 | J40: 53.087 | K40: 76.082
A41: Total Assets | B41: 1314.077 | C41: 1657.541 | D41: 1998.483 | E41: 2084.711 | F41: 3281.354 | G41: 4185.215 | H41: 4942.478 | I41: 5607.038 | J41: 7091.941 | K41: 7603.292
A42: Liabilities & Shareholders' Equity
A43: Current
A44: ST Debt & Curr. Portion LT Debt | B44: 0 | C44: 0 | D44: 0 | E44: 0 | F44: 128.497 | G44: 166.091 | H44: 188.996 | I44: 207.972 | J44: 249.27 | K44: 275.154
A45: Accounts Payable | B45: 10.381 | C45: 24.846 | D45: 24.646 | E45: 95.533 | F45: 79.997 | G45: 172.246 | H45: 289.728 | I45: 172.732 | J45: 348.441 | K45: 271.406
A46: Income Tax Payable | B46: 37.736 | C46: 30.29 | D46: 15.7 | E46: 67.412 | F46: 26.436 | G46: 8.357 | H46: 133.852 | I46: 174.221 | J46: 12.098 | K46: 183.126
A47: Other Current Liabilities | B47: 177.387 | C47: 186.313 | D47: 252.252 | E47: 337.532 | F47: 385.488 | G47: 536.484 | H47: 792.758 | I47: 937.273 | J47: 1021.452 | K47: 1109.944
A48: Accrued Payroll | B48: 43.524 | C48: 55.238 | D48: 70.141 | E48: 109.181 | F48: 133.688 | G48: 130.171 | H48: 204.921 | I48: 248.167 | J48: 326.11 | K48: 204.543
A49: Miscellaneous Current Liabilities | B49: 133.863 | C49: 131.075 | D49: 182.111 | E49: 228.351 | F49: 251.8 | G49: 406.313 | H49: 587.837 | I49: 689.106 | J49: 695.342 | K49: 905.401
A50: Total Current Liabilities | B50: 225.504 | C50: 241.449 | D50: 292.598 | E50: 500.477 | F50: 620.418 | G50: 883.178 | H50: 1405.334 | I50: 1492.198 | J50: 1631.261 | K50: 1839.63
A51: Long-Term
A52: Long-Term Debt | B52: 0 | C52: 0 | D52: 0 | E52: 0 | F52: 611.464 | G52: 632.59 | H52: 692.056 | I52: 862.362 | J52: 1154.012 | K52: 1300.637
A53: Capital and Operating Lease Obligations | B53: 0 | C53: 0 | D53: 0 | E53: 0 | F53: 611.464 | G53: 632.59 | H53: 692.056 | I53: 862.362 | J53: 1154.012 | K53: 1300.637
A54: Deferred Tax Liabilities | B54: 10.759 | C54: 7.262 | D54: 1.336 | E54: 14.249 | F54: 43.432 | G54: 58.755 | H54: 53.352 | I54: 55.084 | J54: 29.522 | K54: 98.188
A55: Other Liabilities | B55: 50.332 | C55: 48.857 | D55: 107.589 | E55: 124.01 | F55: 53.822 | G55: 52.126 | H55: 51.69 | I55: 48.595 | J55: 45.065 | K55: 40.79
A56: Other Liabilities (excl. Deferred Income) | B56: 50.332 | C56: 48.857 | D56: 107.589 | E56: 124.01 | F56: 53.822 | G56: 52.126 | H56: 51.69 | I56: 48.595 | J56: 45.065 | K56: 40.79
A57: Total Liabilities | B57: 286.595 | C57: 297.568 | D57: 401.523 | E57: 638.736 | F57: 1329.136 | G57: 1626.649 | H57: 2202.432 | I57: 2458.239 | J57: 2859.86 | K57: 3279.245
A58: Equity
A59: Common Equity | B59: 1027.482 | C59: 1359.973 | D59: 1596.96 | E59: 1445.975 | F59: 1952.218 | G59: 2558.566 | H59: 2740.046 | I59: 3148.799 | J59: 4232.081 | K59: 4324.047
A60: Common Stock Par/Carry Value | B60: 0.637 | C60: 0.637 | D60: 0.628 | E60: 0.608 | F60: 0.621 | G60: 0.626 | H60: 0.616 | I60: 0.611 | J60: 0.606 | K60: 0.581
A61: Additional Paid-In Capital/Capital Surplus | B61: 245.533 | C61: 266.622 | D61: 284.253 | E61: 315.285 | F61: 355.541 | G61: 388.667 | H61: 422.507 | I61: 474.645 | J61: 575.369 | K61: 638.19
A62: Retained Earnings | B62: 1019.515 | C62: 1294.214 | D62: 1455.002 | E62: 1346.89 | F62: 1820.637 | G62: 2346.428 | H62: 2512.84 | I62: 2926.127 | J62: 3920.362 | K62: 4109.717
A63: Cumulative Translation Adjustment/Unrealized For. Exch. Gain | B63: -238.203 | C63: -201.5 | D63: -142.923 | E63: -216.808 | F63: -224.581 | G63: -177.155 | H63: -195.917 | I63: -252.584 | J63: -264.256
A64: Other Appropriated Reserves | B64: 0 | C64: 0 | K64: -424.441
A65: Total Shareholders' Equity | B65: 1027.482 | C65: 1359.973 | D65: 1596.96 | E65: 1445.975 | F65: 1952.218 | G65: 2558.566 | H65: 2740.046 | I65: 3148.799 | J65: 4232.081 | K65: 4324.047
A66: Total Equity | B66: 1027.482 | C66: 1359.973 | D66: 1596.96 | E66: 1445.975 | F66: 1952.218 | G66: 2558.566 | H66: 2740.046 | I66: 3148.799 | J66: 4232.081 | K66: 4324.047
A67: Total Liabilities & Shareholders' Equity | B67: 1314.077 | C67: 1657.541 | D67: 1998.483 | E67: 2084.711 | F67: 3281.354 | G67: 4185.215 | H67: 4942.478 | I67: 5607.038 | J67: 7091.941 | K67: 7603.292
A68: Per Share
A69: Book Value per Share | B69: 7.48424 | C69: 9.92066 | D69: 11.79169 | E69: 11.04371 | F69: 14.97685 | G69: 19.62798 | H69: 21.32332 | I69: 24.73118 | J69: 33.52887 | K69: 35.65283
A70: Tangible Book Value per Share | B70: 7.303767 | C70: 9.741518 | D70: 11.609462 | E70: 10.858583 | F70: 14.789488 | G70: 16.04573 | H70: 17.75772 | I70: 24.369067 | J70: 33.338071 | K70: 34.241322
A71: All figures in millions of U.S. Dollar except per share items.
A73: LULU-US
A74: Balance Sheet (M)
B75: Jan '21 | C75: Jan '22 | D75: Jan '23 | E75: Jan '24 | F75: Jan '25 | G75: Jan '26E | H75: Jan '27E | I75: Jan '28E | J75: Jan '29E | K75: Jan '30E
A76: Current Assets | B76: 2124.4 | C76: 2615 | D76: 3159 | E76: 4061 | F76: 3980 | G76: 4440.7 | H76: 5210.49 | I76: 4887 | J76: 5163 | K76: 5632
A77: Current Liabilities | B77: 883.2 | C77: 1405 | D77: 1492 | E77: 1631 | F77: 1840 | G77: 1879.5 | H77: 1949.67 | I77: 1697 | J77: 1656 | K77: 1774
A78: Total Assets | B78: 4185.2 | C78: 4942 | D78: 5607 | E78: 7091.97 | F78: 7603 | G78: 8471.72 | H78: 9505.85 | I78: 9518 | J78: 10010 | K78: 10660
A79: Short-Term Debt | B79: - | C79: 0 | D79: 0 | E79: 0 | F79: 0 | G79: - | H79: - | I79: - | J79: - | K79: -
A80: Long-Term Debt | B80: - | C80: 0 | D80: 0 | E80: 577 | F80: 0 | G80: - | H80: - | I80: - | J80: - | K80: -
A81: Total Debt | B81: 0 | C81: 0 | D81: 0 | E81: 0 | F81: 0 | G81: 0 | H81: 0 | I81: - | J81: - | K81: -
A82: Intangible Assets | B82: 467 | C82: 458.1 | D82: 46 | E82: 24 | F82: 171 | G82: 174.334 | H82: 174.334 | I82: 167 | J82: 167 | K82: 167
A83: Total Goodwill | B83: 1335.48 | C83: 386.88 | D83: 24.144 | E83: 24.083 | F83: 159.518 | G83: 159.518 | H83: 159.518 | I83: 159.518 | J83: - | K83: -
A84: Net Debt | B84: -1150.76 | C84: -1259.87 | D84: -1154.9 | E84: -2244 | F84: -1984.15 | G84: -2408.27 | H84: -3308.39 | I84: -4138.75 | J84: -3057.43 | K84: -2972
A85: Working Capital | B85: - | C85: 1209.52 | D85: 1667.13 | E85: 2399.09 | F85: 2140.84 | G85: 2365.66 | H85: 2812.41 | I85: 3190 | J85: 3508 | K85: 3857
A86: Minority Interest | B86: 0 | C86: 0 | D86: 0 | E86: 22.5 | F86: 0 | G86: 0 | H86: 0 | I86: 0 | J86: - | K86: -
A87: Shareholder Equity | B87: 2558.6 | C87: 2740 | D87: 3149 | E87: 4232 | F87: 4324 | G87: 5086.68 | H87: 6059.1 | I87: 6909.88 | J87: 6786 | K87: 7317

Sheet CF
A1: lululemon athletica inc. (LULU)
A2: $226.11
A5: lululemon athletica inc.
A6: LULU 550021109 B23FN39 NASDAQ Common stock
A7: Source: FactSet Fundamentals
B8: JAN '16 | C8: JAN '17 | D8: JAN '18 | E8: JAN '19 | F8: JAN '20 | G8: JAN '21 | H8: JAN '22 | I8: JAN '23 | J8: JAN '24 | K8: JAN '25 | L8: APR '25
L9: LTM
A10: Operating Activities
A11: Net Income / Starting Line | B11: 266.047 | C11: 303.381 | D11: 258.662 | E11: 483.801 | F11: 645.596 | G11: 588.913 | H11: 975.322 | I11: 854.8 | J11: 1550.19 | K11: 1814.616 | L11: 1807.767
A12: Depreciation, Depletion & Amortization | B12: 73.383 | C12: 87.697 | D12: 108.235 | E12: 122.484 | F12: 161.933 | G12: 185.478 | H12: 224.206 | I12: 291.791 | J12: 379.384 | K12: 446.524 | L12: 465.294
A13: Depreciation and Depletion | B13: 72.573 | C13: 86.997 | D13: 108.235 | E13: 122.484 | F13: 161.933 | H13: 215.424 | I13: 283.039 | J13: 374.374 | K13: 443.789 | L13: 460.929
A14: Amortization of Intangible Assets | B14: 0.81 | C14: 0.7 | H14: 8.782 | I14: 8.752 | J14: 5.01 | K14: 2.735 | L14: 4.365
A15: Deferred Taxes & Investment Tax Credit | B15: 11.142 | C15: -17.563 | D15: -11.416 | E15: 16.786 | F15: 24.129 | G15: 34.908 | H15: -5.18 | I15: 3.042 | J15: -28.383 | K15: 57.451 | L15: 57.451
A16: Deferred Taxes | B16: 11.142 | C16: -17.563 | D16: -11.416 | E16: 16.786 | F16: 24.129 | G16: 34.908 | H16: -5.18 | I16: 3.042 | J16: -28.383 | K16: 57.451 | L16: 57.451
A17: Other Funds | B17: 7.911 | C17: 10.078 | D17: 29.228 | E17: 6.833 | F17: 31.729 | G17: 41.586 | H17: 65.629 | I17: 413.822 | J17: 195.75 | K17: 6.017 | L17: -43.854
A18: Funds from Operations | B18: 358.483 | C18: 383.593 | D18: 384.709 | E18: 629.904 | F18: 863.387 | G18: 850.885 | H18: 1259.977 | I18: 1563.455 | J18: 2096.941 | K18: 2324.608 | L18: 2286.658
A19: Changes in Working Capital | B19: -59.743 | C19: 0.603 | D19: 104.628 | E19: 112.875 | F19: -194.071 | G19: -47.549 | H19: 129.131 | I19: -596.992 | J19: 199.223 | K19: -51.895 | L19: -260.423
A20: Receivables | K20: 1.626
A21: Inventories | B21: -83.286 | C21: -5.403 | D21: -21.178 | E21: -85.942 | F21: -117.591 | G21: -96.548 | H21: -323.609 | I21: -510.51 | J21: 66.584 | K21: -156.085 | L21: -293.979
A22: Accounts Payable | B22: 1.247 | C22: 14.08 | D22: -1.551 | E22: 71.962 | F22: -14.81 | G22: 82.663 | H22: 117.655 | I22: -107.28 | J22: 177.367 | K22: -57.044 | L22: 47.811
A23: Income Taxes Payable | B23: 19.47 | C23: -10.02 | D23: -16.47 | E23: 52.597 | F23: -40.264 | G23: -24.125 | H23: 120.778 | I23: 35.986 | J23: -173.196 | K23: 157.205 | L23: -44.206
A24: Other Accruals | B24: 39.698 | C24: -8.49 | D24: 47.363 | E24: 45.912 | F24: 15.728 | G24: 92.469 | H24: 179.151 | I24: 112.618 | J24: -1.407 | K24: 81.029 | L24: 125.402
A25: Other Assets/Liabilities | B25: -36.872 | C25: 10.436 | D25: 96.464 | E25: 28.346 | F25: -37.134 | G25: -102.008 | H25: 35.156 | I25: -127.806 | J25: 129.875 | K25: -78.626 | L25: -78.573
A26: Net Operating Cash Flow | B26: 298.74 | C26: 384.196 | D26: 489.337 | E26: 742.779 | F26: 669.316 | G26: 803.336 | H26: 1389.108 | I26: 966.463 | J26: 2296.164 | K26: 2272.713 | L26: 2026.235
A27: Investing Activities
A28: Capital Expenditures | B28: -143.487 | C28: -149.511 | D28: -157.864 | E28: -225.807 | F28: -283.048 | G28: -229.226 | H28: -394.502 | I28: -638.657 | J28: -651.865 | K28: -689.232 | L28: -710.814
A29: Capital Expenditures (Fixed Assets) | B29: -143.487 | C29: -149.511 | D29: -157.864 | E29: -225.807 | F29: -283.048 | G29: -229.226 | H29: -394.502 | I29: -638.657 | J29: -651.865 | K29: -689.232 | L29: -710.814
A30: Net Assets from Acquisitions | E30: 0 | F30: 0 | G30: -452.581 | H30: 0 | I30: 0 | J30: 0 | K30: -154.146 | L30: -154.146
A31: Purchase/Sale of Investments | B31: 0 | C31: 0 | D31: -7.203 | E31: 0 | F31: 0 | G31: 0 | H31: 0 | I31: 0 | J31: 0 | K31: 0 | L31: 0
A32: Purchase of Investments | C32: 0 | D32: 7.203 | E32: 0 | F32: 0 | G32: 0 | H32: 0 | I32: 0 | J32: 0 | K32: 0 | L32: 0
A33: Other Funds | B33: 0 | C33: 0 | D33: -8.325 | E33: -16.987 | F33: 4.64 | G33: -13.725 | H33: -33.389 | I33: 68.72 | J33: -2.267 | K33: 45.204 | L33: 91.481
A34: Other Uses | B34: 0 | C34: 0 | D34: -8.325 | E34: -16.987 | F34: 0 | G34: -14.607 | H34: -33.389 | I34: 0 | J34: -2.267 | K34: -5.009 | L34: -7.403
A35: Other Sources | B35: 0 | C35: 0 | D35: 0 | E35: 0 | F35: 4.64 | G35: 0.882 | H35: 0 | I35: 68.72 | J35: 0 | K35: 50.213 | L35: 98.884
A36: Net Investing Cash Flow | B36: -143.487 | C36: -149.511 | D36: -173.392 | E36: -242.794 | F36: -278.408 | G36: -695.532 | H36: -427.891 | I36: -569.937 | J36: -654.132 | K36: -798.174 | L36: -773.479
A37: Financing Activities
A38: Change in Capital Stock | B38: -269.489 | C38: -22.42 | D38: -94.633 | E38: -580.69 | F38: -155.229 | G38: -48.4 | H38: -794.408 | I38: -432.297 | J38: -516.222 | K38: -1617.066 | L38: -1755.198
A39: Repurchase of Common & Preferred Stk. | B39: -274.193 | C39: -29.327 | D39: -100.261 | E39: -598.34 | F39: -173.399 | G39: -63.663 | H39: -812.602 | I39: -444.001 | J39: -558.652 | K39: -1636.879 | L39: -1771.839
A40: Sale of Common & Preferred Stock | B40: 4.704 | C40: 6.907 | D40: 5.628 | E40: 17.65 | F40: 18.17 | G40: 15.263 | H40: 18.194 | I40: 11.704 | J40: 42.43 | K40: 19.813 | L40: 16.641
A41: Proceeds from Stock Options | B41: 4.704 | C41: 6.907 | D41: 5.628 | E41: 17.65 | F41: 18.17 | G41: 15.263 | H41: 18.194 | I41: 11.704 | J41: 42.43 | K41: 19.813 | L41: 16.641
A42: Other Funds | B42: -4.204 | C42: -1.995 | D42: -3.229 | E42: -9.524 | F42: -21.944 | G42: -32.388 | H42: -50.579 | I42: -35.19 | J42: -32.606 | K42: -35.442 | L42: -36.656
A43: Other Uses | B43: -4.204 | C43: -3.268 | D43: -3.229 | E43: -9.524 | F43: -21.944 | G43: -32.388 | H43: -50.579 | I43: -35.19 | J43: -32.606 | K43: -35.442 | L43: -36.656
A44: Other Sources | B44: 0 | C44: 1.273 | D44: 0 | E44: 0 | F44: 0 | G44: 0 | H44: 0 | I44: 0 | J44: 0 | K44: 0 | L44: 0
A45: Net Financing Cash Flow | B45: -273.693 | C45: -24.415 | D45: -97.862 | E45: -590.214 | F45: -177.173 | G45: -80.788 | H45: -844.987 | I45: -467.487 | J45: -548.828 | K45: -1652.508 | L45: -1791.854
A46: All Activities
A47: Exchange Rate Effect | B47: -44.557 | C47: 23.094 | D47: 37.572 | E47: -18.952 | F47: -1.55 | G47: 29.996 | H47: -6.876 | I47: -34.043 | J47: -4.1 | K47: -81.666 | L47: -36.302
A48: Net Change in Cash | B48: -162.997 | C48: 233.364 | D48: 255.655 | E48: -109.181 | F48: 212.185 | G48: 57.012 | H48: 109.354 | I48: -105.004 | J48: 1089.104 | K48: -259.635 | L48: -575.4
A49: Free Cash Flow | B49: 155.253 | C49: 234.685 | D49: 331.473 | E49: 516.972 | F49: 386.268 | G49: 574.11 | H49: 994.606 | I49: 327.806 | J49: 1644.299 | K49: 1583.481 | L49: 1315.421
A50: Free Cash Flow per Share | B50: 1.104139 | C50: 1.709261 | D50: 2.433758 | E50: 3.858835 | F50: 2.949624 | G50: 4.386839 | H50: 7.633493 | I50: 2.560644 | J50: 12.941122 | K50: 12.776706 | L50: 10.885372
A51: Free Cash Flow Yield (%) | B51: 1.778861 | C51: 2.558009 | D51: 3.07759 | E51: 2.640867 | F51: 1.232142 | G51: 1.334684 | H51: 2.416351 | I51: 0.823756 | J51: 2.707178 | K51: 3.120684 | L51: 3.924637
A52: All figures in millions of U.S. Dollar except per share items.
A54: Estimates
A55: LULU-US
A56: Cash Flow (M)
B57: Jan '21 | C57: Jan '22 | D57: Jan '23 | E57: Jan '24 | F57: Jan '25 | G57: Jan '26E | H57: Jan '27E | I57: Jan '28E | J57: Jan '29E | K57: Jan '30E
A58: Capital Expenditures | B58: 229.2 | C58: 395 | D58: 639 | E58: 652 | F58: 689 | G58: 757.291 | H58: 806.813 | I58: 827.477 | J58: 860.303 | K58: 787
A59: Guidance (Low) | B59: - | C59: 375 | D59: 630 | E59: 670 | F59: 670 | G59: 740 | H59: - | I59: - | J59: - | K59: -
A60: Guidance (High) | B60: - | C60: 385 | D60: 655 | E60: 690 | F60: 690 | G60: 760 | H60: - | I60: - | J60: - | K60: -
A61: Free Cash Flow | B61: 574 | C61: 995 | D61: 327.806 | E61: 1644.3 | F61: 1583 | G61: 1231.12 | H61: 1529.67 | I61: 1585.2 | J61: 1818.51 | K61: 2020
A62: Unlevered Free Cash Flow | B62: 601.5 | C62: 1034.1 | D62: 757.8 | E62: 1673.4 | F62: 1513.1 | G62: 861.8 | H62: 1223.4 | I62: - | J62: - | K62: -
A63: Cash Flow from Operations | B63: 803.15 | C63: 1389 | D63: 966 | E63: 2296.08 | F63: 2273 | G63: 2091.61 | H63: 2360.65 | I63: 2417 | J63: 2666 | K63: 2807
A64: Cash Flow from Investing | B64: -695.5 | C64: -427.95 | D64: -570 | E64: -654 | F64: -798 | G64: -710.267 | H64: -801.333 | I64: -834 | J64: -813 | K64: -787
A65: Cash Flow from Financing | B65: -80.8 | C65: -845 | D65: -467.25 | E65: -549 | F65: -1653 | G65: -1182.73 | H65: -929.4 | I65: -1474 | J65: -1594 | K65: -1724
